Workbook

Sheet 01_README
A1: FMCG Sales Performance & Target Tracking System
A2: Excel 2019 Portfolio Project - Synthetic & Illustrative Data
A4: Project Overview
A5: This workbook demonstrates an end-to-end FMCG sales performance and target tracking system built in Microsoft Excel 2019. The model covers company-to-distributor primary sales, salesperson targets, distributor stock, collections, product performance, forecasting, and management reporting.
A7: Portfolio Data Disclaimer
A8: This portfolio project is based on real-world FMCG sales reporting and analytical responsibilities previously performed by the author. All company names, customer/distributor names, products, transactions, targets, inventory records, collection records, and financial figures in this workbook are synthetic and illustrative. The workbook does not reproduce or disclose confidential employer data.
A10: Business Scope
A11: Sales Scope: Company-to-Distributor Primary Sales (Sell-In)
A12: Secondary Sales Available: No — distributor-to-retailer sell-out data is not included.
A13: Inventory Scope: Distributor Stock / Inventory Snapshots
A14: Reporting Period: 2026
A15: Forecast Horizon: 3 Months
... A49: 18_Model_Documentation — Technical model documentation, methodology, formula library, and automation notes

Sheet 02_Control_Panel
A1: Section 1 — Model Controls
A2: Parameter | B2: Value | C2: Description
A3: Reporting Year | B3: 2026 | C3: Primary reporting year for the portfolio model
A4: Latest Actual Month | B4: 46382 | C4: Latest month with actual company-to-distributor sales
A5: Latest Inventory Snapshot | B5: 46387 | C5: Latest distributor inventory snapshot used in analysis
A6: Forecast Horizon (Months) | B6: 3 | C6: Number of future months included in the forecast
A7: Near Target Threshold | B7: 0.9 | C7: Changeable threshold. Achievement at or above this level is classified as Near Target when the Target Achievement Threshold has not been reached.
A8: Target Achievement Threshold | B8: 1 | C8: Changeable threshold. Achievement at or above this level is classified as Achieved.
A9: Forecast Method | B9: 3-Month Rolling Average — Recursive Forecast | C9: Forecast method used for 2027 planning estimates
A10: Section 2 — Model Statistics
A11: Number of Cities | B11: =COUNTA(tblCities[City ID]) -> 4 | C11: Number of cities currently included in the model
A12: Number of RSMs | B12: =SUMPRODUCT((tblSalesTeam[RSM ID]<>"")/COUNTIF(tblSalesTeam[RSM ID],tblSalesTeam[RSM ID]&"")) -> 4 | C12: Number of Regional Sales Managers currently included
A13: Number of Salespeople | B13: =COUNTA(tblSalesTeam[Salesperson ID]) -> 12 | C13: Number of salespeople currently included
A14: Number of Distributors | B14: =COUNTA(tblDistributors[Distributor ID]) -> 12 | C14: Number of active distributors currently included
A15: Number of Products | B15: =COUNTA(tblProducts[Product ID]) -> 56 | C15: Number of products/SKUs currently included
A16: Sales Transactions | B16: =COUNTA(tblSalesTransactions[Transaction ID]) -> 300 | C16: Number of company-to-distributor sales transactions
A17: Collection Records | B17: =COUNTA(tblCollections[Collection ID]) -> 72 | C17: Number of distributor collection records
A18: Inventory Records | B18: =COUNTA(tblInventory[Distributor ID]) -> 192 | C18: 12 distributors × 4 quarterly snapshots × 4 selected SKUs = 192 inventory records
A19: Sales Target Records | B19: =COUNTA(tblSalesTargets[Salesperson ID]) -> 144 | C19: Number of monthly salesperson target records for 2026
A20: Portfolio & Business Scope
A21: Data Type | B21: Synthetic / Illustrative | C21: Portfolio dataset created for demonstration; workflow and business context are based on real-world FMCG reporting experience
A22: Sales Scope | B22: Company-to-Distributor Primary Sales | C22: Sales represent company sell-in to distributors
A23: Secondary Sales Available | B23: No | C23: Distributor-to-retailer sell-out data is not included
A24: Inventory Scope | B24: Distributor Stock | C24: Inventory represents distributor stock snapshots
A25: Forecast Status | B25: Indicative Planning Estimate | C25: Forecast is an illustrative planning estimate and is not a guaranteed future result
A26: Control Usage
A27: Control parameters are linked to model calculations where applicable. Near Target Threshold, Target Achievement Threshold, and Latest Inventory Snapshot directly influence model calculations. Model statistics are automatically derived from the underlying Excel Tables. Reporting Year, Forecast Horizon, and Forecast Method document the model scope and assumptions and do not independently rebuild the underlying dataset.
A28: Portfolio Data Disclaimer
A29: This portfolio project is based on real-world FMCG sales reporting and analytical responsibilities previously performed by the author. All company names, customer/distributor names, products, transactions, targets, inventory records, collection records, and financial figures in this workbook are synthetic and illustrative. The workbook does not reproduce or disclose confidential employer data.

Sheet 03_Cities
A1: City ID | B1: City | C1: Region | D1: Status
A2: C001 | B2: Karachi | C2: Sindh | D2: Active
A3: C002 | B3: Lahore | C3: Punjab | D3: Active
A4: C003 | B4: Islamabad | C4: Federal | D4: Active
A5: C004 | B5: Rawalpindi | C5: Punjab | D5: Active

Sheet 04_Sales_Team
A1: RSM ID | B1: RSM Name | C1: Salesperson ID | D1: Salesperson Name | E1: City ID
A2: R001 | B2: Ali Khan | C2: SP001 | D2: Ahmed Raza | E2: C001
A3: R001 | B3: Ali Khan | C3: SP002 | D3: Bilal Ahmed | E3: C001
A4: R001 | B4: Ali Khan | C4: SP003 | D4: Farhan Malik | E4: C001
A5: R002 | B5: Hamza Malik | C5: SP004 | D5: Danish Ali | E5: C002
A6: R002 | B6: Hamza Malik | C6: SP005 | D6: Usman Tariq | E6: C002
A7: R002 | B7: Hamza Malik | C7: SP006 | D7: Saad Ahmed | E7: C002
A8: R003 | B8: Imran Shah | C8: SP007 | D8: Hassan Raza | E8: C003
A9: R003 | B9: Imran Shah | C9: SP008 | D9: Kamran Ali | E9: C003
A10: R003 | B10: Imran Shah | C10: SP009 | D10: Salman Ahmed | E10: C003
A11: R004 | B11: Fahad Khan | C11: SP010 | D11: Adeel Hussain | E11: C004
A12: R004 | B12: Fahad Khan | C12: SP011 | D12: Rizwan Ali | E12: C004
A13: R004 | B13: Fahad Khan | C13: SP012 | D13: Naveed Ahmed | E13: C004

Sheet 05_Distributors
A1: Distributor ID | B1: Distributor Name | C1: City ID | D1: RSM ID | E1: Salesperson ID | F1: Status
A2: D001 | B2: Karachi Distributors | C2: C001 | D2: R001 | E2: SP001 | F2: Active
A3: D002 | B3: Metro Wholesale Karachi | C3: C001 | D3: R001 | E3: SP002 | F3: Active
A4: D003 | B4: Sindh Trade Network | C4: C001 | D4: R001 | E4: SP003 | F4: Active
A5: D004 | B5: Lahore Trading Co. | C5: C002 | D5: R002 | E5: SP004 | F5: Active
A6: D005 | B6: Punjab Distribution House | C6: C002 | D6: R002 | E6: SP005 | F6: Active
A7: D006 | B7: Lahore Wholesale Mart | C7: C002 | D7: R002 | E7: SP006 | F7: Active
A8: D007 | B8: Capital Distribution Co. | C8: C003 | D8: R003 | E8: SP007 | F8: Active
A9: D008 | B9: Islamabad Trade Link | C9: C003 | D9: R003 | E9: SP008 | F9: Active
A10: D009 | B10: Capital Wholesale Network | C10: C003 | D10: R003 | E10: SP009 | F10: Active
A11: D010 | B11: Rawalpindi Distribution Co. | C11: C004 | D11: R004 | E11: SP010 | F11: Active
A12: D011 | B12: Potohar Trade House | C12: C004 | D12: R004 | E12: SP011 | F12: Active
A13: D012 | B13: Rawalpindi Wholesale Mart | C13: C004 | D13: R004 | E13: SP012 | F13: Active

Sheet 06_Products
A1: Product ID | B1: Brand | C1: Product Name | D1: Category | E1: Sub-Category | F1: Pack Size | G1: Unit
A2: P001 | B2: Morning Harvest | C2: Corn Flakes Original | D2: Morning Cereals | E2: Corn Flakes | F2: 250g | G2: Box
A3: P002 | B3: Morning Harvest | C3: Corn Flakes Original | D3: Morning Cereals | E3: Corn Flakes | F3: 500g | G3: Box
A4: P003 | B4: Morning Harvest | C4: Corn Flakes Original | D4: Morning Cereals | E4: Corn Flakes | F4: 1kg | G4: Box
A5: P004 | B5: Morning Harvest | C5: Honey Corn Flakes | D5: Morning Cereals | E5: Corn Flakes | F5: 250g | G5: Box
A6: P005 | B6: Morning Harvest | C6: Honey Corn Flakes | D6: Morning Cereals | E6: Corn Flakes | F6: 500g | G6: Box
A7: P006 | B7: Morning Harvest | C7: Chocolate Corn Flakes | D7: Morning Cereals | E7: Corn Flakes | F7: 250g | G7: Box
A8: P007 | B8: Morning Harvest | C8: Chocolate Corn Flakes | D8: Morning Cereals | E8: Corn Flakes | F8: 500g | G8: Box
A9: P008 | B9: Morning Harvest | C9: Frosted Flakes | D9: Morning Cereals | E9: Flakes | F9: 250g | G9: Box
A10: P009 | B10: Morning Harvest | C10: Frosted Flakes | D10: Morning Cereals | E10: Flakes | F10: 500g | G10: Box
A11: P010 | B11: Morning Harvest | C11: Bran Flakes | D11: Morning Cereals | E11: Healthy Cereals | F11: 250g | G11: Box
A12: P011 | B12: Morning Harvest | C12: Bran Flakes | D12: Morning Cereals | E12: Healthy Cereals | F12: 500g | G12: Box
... A57: P056 | B57: Melegatti | C57: Filled Croissant Vanilla | D57: Cakes & Croissants | E57: Croissants | F57: 6 Pack | G57: Pack

Sheet 07_Calendar
A1: Date | B1: Year | C1: Month No | D1: Month | E1: Quarter | F1: Week No | G1: Week Start | H1: Week End | I1: Day | J1: Day No | K1: Month-Year
A2: =DATE(2026,1,1) -> 46023 | B2: =YEAR(A2) -> 2026 | C2: =MONTH(A2) -> 1 | D2: =TEXT(A2,"mmmm") -> January | E2: ="Q"&ROUNDUP(MONTH(A2)/3,0) -> Q1 | F2: =WEEKNUM(A2,2) -> 1 | G2: =A2-WEEKDAY(A2,2)+1 -> 46020 | H2: =G2+6 -> 46026 | I2: =TEXT(A2,"dddd") -> Thursday | J2: =WEEKDAY(A2,2) -> 4 | K2: =TEXT(A2,"mmm-yyyy") -> Jan-2026
A3: =A2+1 -> 46024 | B3: =YEAR(A3) -> 2026 | C3: =MONTH(A3) -> 1 | D3: =TEXT(A3,"mmmm") -> January | E3: ="Q"&ROUNDUP(MONTH(A3)/3,0) -> Q1 | F3: =WEEKNUM(A3,2) -> 1 | G3: =A3-WEEKDAY(A3,2)+1 -> 46020 | H3: =G3+6 -> 46026 | I3: =TEXT(A3,"dddd") -> Friday | J3: =WEEKDAY(A3,2) -> 5 | K3: =TEXT(A3,"mmm-yyyy") -> Jan-2026
A4: =A3+1 -> 46025 | B4: =YEAR(A4) -> 2026 | C4: =MONTH(A4) -> 1 | D4: =TEXT(A4,"mmmm") -> January | E4: ="Q"&ROUNDUP(MONTH(A4)/3,0) -> Q1 | F4: =WEEKNUM(A4,2) -> 1 | G4: =A4-WEEKDAY(A4,2)+1 -> 46020 | H4: =G4+6 -> 46026 | I4: =TEXT(A4,"dddd") -> Saturday | J4: =WEEKDAY(A4,2) -> 6 | K4: =TEXT(A4,"mmm-yyyy") -> Jan-2026
A5: =A4+1 -> 46026 | B5: =YEAR(A5) -> 2026 | C5: =MONTH(A5) -> 1 | D5: =TEXT(A5,"mmmm") -> January | E5: ="Q"&ROUNDUP(MONTH(A5)/3,0) -> Q1 | F5: =WEEKNUM(A5,2) -> 1 | G5: =A5-WEEKDAY(A5,2)+1 -> 46020 | H5: =G5+6 -> 46026 | I5: =TEXT(A5,"dddd") -> Sunday | J5: =WEEKDAY(A5,2) -> 7 | K5: =TEXT(A5,"mmm-yyyy") -> Jan-2026
A6: =A5+1 -> 46027 | B6: =YEAR(A6) -> 2026 | C6: =MONTH(A6) -> 1 | D6: =TEXT(A6,"mmmm") -> January | E6: ="Q"&ROUNDUP(MONTH(A6)/3,0) -> Q1 | F6: =WEEKNUM(A6,2) -> 2 | G6: =A6-WEEKDAY(A6,2)+1 -> 46027 | H6: =G6+6 -> 46033 | I6: =TEXT(A6,"dddd") -> Monday | J6: =WEEKDAY(A6,2) -> 1 | K6: =TEXT(A6,"mmm-yyyy") -> Jan-2026
A7: =A6+1 -> 46028 | B7: =YEAR(A7) -> 2026 | C7: =MONTH(A7) -> 1 | D7: =TEXT(A7,"mmmm") -> January | E7: ="Q"&ROUNDUP(MONTH(A7)/3,0) -> Q1 | F7: =WEEKNUM(A7,2) -> 2 | G7: =A7-WEEKDAY(A7,2)+1 -> 46027 | H7: =G7+6 -> 46033 | I7: =TEXT(A7,"dddd") -> Tuesday | J7: =WEEKDAY(A7,2) -> 2 | K7: =TEXT(A7,"mmm-yyyy") -> Jan-2026
A8: =A7+1 -> 46029 | B8: =YEAR(A8) -> 2026 | C8: =MONTH(A8) -> 1 | D8: =TEXT(A8,"mmmm") -> January | E8: ="Q"&ROUNDUP(MONTH(A8)/3,0) -> Q1 | F8: =WEEKNUM(A8,2) -> 2 | G8: =A8-WEEKDAY(A8,2)+1 -> 46027 | H8: =G8+6 -> 46033 | I8: =TEXT(A8,"dddd") -> Wednesday | J8: =WEEKDAY(A8,2) -> 3 | K8: =TEXT(A8,"mmm-yyyy") -> Jan-2026
A9: =A8+1 -> 46030 | B9: =YEAR(A9) -> 2026 | C9: =MONTH(A9) -> 1 | D9: =TEXT(A9,"mmmm") -> January | E9: ="Q"&ROUNDUP(MONTH(A9)/3,0) -> Q1 | F9: =WEEKNUM(A9,2) -> 2 | G9: =A9-WEEKDAY(A9,2)+1 -> 46027 | H9: =G9+6 -> 46033 | I9: =TEXT(A9,"dddd") -> Thursday | J9: =WEEKDAY(A9,2) -> 4 | K9: =TEXT(A9,"mmm-yyyy") -> Jan-2026
A10: =A9+1 -> 46031 | B10: =YEAR(A10) -> 2026 | C10: =MONTH(A10) -> 1 | D10: =TEXT(A10,"mmmm") -> January | E10: ="Q"&ROUNDUP(MONTH(A10)/3,0) -> Q1 | F10: =WEEKNUM(A10,2) -> 2 | G10: =A10-WEEKDAY(A10,2)+1 -> 46027 | H10: =G10+6 -> 46033 | I10: =TEXT(A10,"dddd") -> Friday | J10: =WEEKDAY(A10,2) -> 5 | K10: =TEXT(A10,"mmm-yyyy") -> Jan-2026
A11: =A10+1 -> 46032 | B11: =YEAR(A11) -> 2026 | C11: =MONTH(A11) -> 1 | D11: =TEXT(A11,"mmmm") -> January | E11: ="Q"&ROUNDUP(MONTH(A11)/3,0) -> Q1 | F11: =WEEKNUM(A11,2) -> 2 | G11: =A11-WEEKDAY(A11,2)+1 -> 46027 | H11: =G11+6 -> 46033 | I11: =TEXT(A11,"dddd") -> Saturday | J11: =WEEKDAY(A11,2) -> 6 | K11: =TEXT(A11,"mmm-yyyy") -> Jan-2026
A12: =A11+1 -> 46033 | B12: =YEAR(A12) -> 2026 | C12: =MONTH(A12) -> 1 | D12: =TEXT(A12,"mmmm") -> January | E12: ="Q"&ROUNDUP(MONTH(A12)/3,0) -> Q1 | F12: =WEEKNUM(A12,2) -> 2 | G12: =A12-WEEKDAY(A12,2)+1 -> 46027 | H12: =G12+6 -> 46033 | I12: =TEXT(A12,"dddd") -> Sunday | J12: =WEEKDAY(A12,2) -> 7 | K12: =TEXT(A12,"mmm-yyyy") -> Jan-2026
A13: =A12+1 -> 46034 | B13: =YEAR(A13) -> 2026 | C13: =MONTH(A13) -> 1 | D13: =TEXT(A13,"mmmm") -> January | E13: ="Q"&ROUNDUP(MONTH(A13)/3,0) -> Q1 | F13: =WEEKNUM(A13,2) -> 3 | G13: =A13-WEEKDAY(A13,2)+1 -> 46034 | H13: =G13+6 -> 46040 | I13: =TEXT(A13,"dddd") -> Monday | J13: =WEEKDAY(A13,2) -> 1 | K13: =TEXT(A13,"mmm-yyyy") -> Jan-2026
A14: =A13+1 -> 46035 | B14: =YEAR(A14) -> 2026 | C14: =MONTH(A14) -> 1 | D14: =TEXT(A14,"mmmm") -> January | E14: ="Q"&ROUNDUP(MONTH(A14)/3,0) -> Q1 | F14: =WEEKNUM(A14,2) -> 3 | G14: =A14-WEEKDAY(A14,2)+1 -> 46034 | H14: =G14+6 -> 46040 | I14: =TEXT(A14,"dddd") -> Tuesday | J14: =WEEKDAY(A14,2) -> 2 | K14: =TEXT(A14,"mmm-yyyy") -> Jan-2026
... A366: =A365+1 -> 46387 | B366: =YEAR(A366) -> 2026 | C366: =MONTH(A366) -> 12 | D366: =TEXT(A366,"mmmm") -> December | E366: ="Q"&ROUNDUP(MONTH(A366)/3,0) -> Q4 | F366: =WEEKNUM(A366,2) -> 53 | G366: =A366-WEEKDAY(A366,2)+1 -> 46384 | H366: =G366+6 -> 46390 | I366: =TEXT(A366,"dddd") -> Thursday | J366: =WEEKDAY(A366,2) -> 4 | K366: =TEXT(A366,"mmm-yyyy") -> Dec-2026

Sheet 08_Sales_Targets
A1: MonthYear | B1: Month No | C1: Salesperson ID | D1: RSM ID | E1: City ID | F1: Target Amount
A2: 46023 | B2: 1 | C2: SP001 | D2: R001 | E2: C001 | F2: 2500000
A3: 46023 | B3: 1 | C3: SP002 | D3: R001 | E3: C001 | F3: 2300000
A4: 46023 | B4: 1 | C4: SP003 | D4: R001 | E4: C001 | F4: 2200000
A5: 46023 | B5: 1 | C5: SP004 | D5: R002 | E5: C002 | F5: 2700000
A6: 46023 | B6: 1 | C6: SP005 | D6: R002 | E6: C002 | F6: 2500000
A7: 46023 | B7: 1 | C7: SP006 | D7: R002 | E7: C002 | F7: 2300000
A8: 46023 | B8: 1 | C8: SP007 | D8: R003 | E8: C003 | F8: 2400000
A9: 46023 | B9: 1 | C9: SP008 | D9: R003 | E9: C003 | F9: 2200000
A10: 46023 | B10: 1 | C10: SP009 | D10: R003 | E10: C003 | F10: 2100000
A11: 46023 | B11: 1 | C11: SP010 | D11: R004 | E11: C004 | F11: 2200000
A12: 46023 | B12: 1 | C12: SP011 | D12: R004 | E12: C004 | F12: 2000000
A13: 46023 | B13: 1 | C13: SP012 | D13: R004 | E13: C004 | F13: 1900000
... A145: 46357 | B145: 12 | C145: SP012 | D145: R004 | E145: C004 | F145: 2280000
F146: =SUBTOTAL(109,tblSalesTargets[Target Amount]) -> 348075000

Sheet 09_Sales_Transactions
A1: Transaction ID | B1: Date | C1: Distributor ID | D1: Salesperson ID | E1: RSM ID | F1: City ID | G1: Product ID | H1: Quantity | I1: Unit Price | J1: Sales Amount
A2: TXN0001 | B2: 46027 | C2: D001 | D2: SP001 | E2: R001 | F2: C001 | G2: P001 | H2: 120 | I2: 850 | J2: =H2*I2 -> 102000
A3: TXN0002 | B3: 46029 | C3: D002 | D3: SP002 | E3: R001 | F3: C001 | G3: P004 | H3: 150 | I3: 900 | J3: =H3*I3 -> 135000
A4: TXN0003 | B4: 46031 | C4: D003 | D4: SP003 | E4: R001 | F4: C001 | G4: P014 | H4: 80 | I4: 1450 | J4: =H4*I4 -> 116000
A5: TXN0004 | B5: 46028 | C5: D004 | D5: SP004 | E5: R002 | F5: C002 | G5: P032 | H5: 100 | I5: 2200 | J5: =H5*I5 -> 220000
A6: TXN0005 | B6: 46032 | C6: D005 | D6: SP005 | E6: R002 | F6: C002 | G6: P035 | H6: 90 | I6: 2400 | J6: =H6*I6 -> 216000
A7: TXN0006 | B7: 46036 | C7: D006 | D7: SP006 | E7: R002 | F7: C002 | G7: P041 | H7: 130 | I7: 1250 | J7: =H7*I7 -> 162500
A8: TXN0007 | B8: 46030 | C8: D007 | D8: SP007 | E8: R003 | F8: C003 | G8: P002 | H8: 140 | I8: 1450 | J8: =H8*I8 -> 203000
A9: TXN0008 | B9: 46034 | C9: D008 | D9: SP008 | E9: R003 | F9: C003 | G9: P015 | H9: 75 | I9: 2600 | J9: =H9*I9 -> 195000
A10: TXN0009 | B10: 46040 | C10: D009 | D10: SP009 | E10: R003 | F10: C003 | G10: P049 | H10: 160 | I10: 1100 | J10: =H10*I10 -> 176000
A11: TXN0010 | B11: 46033 | C11: D010 | D11: SP010 | E11: R004 | F11: C004 | G11: P005 | H11: 130 | I11: 950 | J11: =H11*I11 -> 123500
A12: TXN0011 | B12: 46038 | C12: D011 | D12: SP011 | E12: R004 | F12: C004 | G12: P043 | H12: 100 | I12: 1200 | J12: =H12*I12 -> 120000
A13: TXN0012 | B13: 46043 | C13: D012 | D13: SP012 | E13: R004 | F13: C004 | G13: P051 | H13: 150 | I13: 1150 | J13: =H13*I13 -> 172500
... A301: TXN0300 | B301: 46378 | C301: D012 | D301: SP012 | E301: R004 | F301: C004 | G301: P056 | H301: 165 | I301: 1350 | J301: =H301*I301 -> 222750
J302: =SUBTOTAL(109,tblSalesTransactions[Sales Amount]) -> 60255750

Sheet 10_Inventory
A1: Snapshot Date | B1: Distributor ID | C1: Product ID | D1: Opening Stock Qty | E1: Closing Stock Qty | F1: Stock Value | G1: Stock Status
A2: 46112 | B2: D001 | C2: P001 | D2: 180 | E2: 145 | F2: 123250 | G2: Normal
A3: 46112 | B3: D001 | C3: P014 | D3: 120 | E3: 92 | F3: 133400 | G3: Normal
A4: 46112 | B4: D001 | C4: P032 | D4: 75 | E4: 58 | F4: 127600 | G4: Normal
A5: 46112 | B5: D001 | C5: P041 | D5: 90 | E5: 74 | F5: 92500 | G5: Normal
A6: 46112 | B6: D002 | C6: P004 | D6: 160 | E6: 128 | F6: 115200 | G6: Normal
A7: 46112 | B7: D002 | C7: P015 | D7: 105 | E7: 82 | F7: 213200 | G7: Normal
A8: 46112 | B8: D002 | C8: P035 | D8: 70 | E8: 61 | F8: 146400 | G8: Normal
A9: 46112 | B9: D002 | C9: P049 | D9: 130 | E9: 98 | F9: 107800 | G9: Normal
A10: 46112 | B10: D003 | C10: P006 | D10: 145 | E10: 118 | F10: 135700 | G10: Normal
A11: 46112 | B11: D003 | C11: P020 | D11: 95 | E11: 76 | F11: 136800 | G11: Normal
A12: 46112 | B12: D003 | C12: P038 | D12: 65 | E12: 51 | F12: 147900 | G12: Normal
A13: 46112 | B13: D003 | C13: P051 | D13: 110 | E13: 87 | F13: 100050 | G13: Normal
... A193: 46387 | B193: D012 | C193: P054 | D193: 47 | E193: 36 | F193: 37800 | G193: Normal

Sheet 11_Collections
A1: Collection ID | B1: Invoice Date | C1: Distributor ID | D1: Salesperson ID | E1: RSM ID | F1: City ID | G1: Invoice Amount | H1: Due Date | I1: Collection Date | J1: Collected Amount | K1: Outstanding Amount | L1: Collection Status
A2: COL001 | B2: 46027 | C2: D001 | D2: SP001 | E2: R001 | F2: C001 | G2: 85000 | H2: 46057 | I2: 46055 | J2: 85000 | K2: =G2-J2 -> 0 | L2: =IF(K2=0,"Paid",IF(J2=0,"Outstanding","Partial")) -> Paid
A3: COL002 | B3: 46030 | C3: D002 | D3: SP002 | E3: R001 | F3: C001 | G3: 92000 | H3: 46060 | I3: 46058 | J3: 92000 | K3: =G3-J3 -> 0 | L3: =IF(K3=0,"Paid",IF(J3=0,"Outstanding","Partial")) -> Paid
A4: COL003 | B4: 46034 | C4: D003 | D4: SP003 | E4: R001 | F4: C001 | G4: 78000 | H4: 46064 | I4: 46063 | J4: 60000 | K4: =G4-J4 -> 18000 | L4: =IF(K4=0,"Paid",IF(J4=0,"Outstanding","Partial")) -> Partial
A5: COL004 | B5: 46037 | C5: D004 | D5: SP004 | E5: R002 | F5: C002 | G5: 105000 | H5: 46067 | I5: 46067 | J5: 105000 | K5: =G5-J5 -> 0 | L5: =IF(K5=0,"Paid",IF(J5=0,"Outstanding","Partial")) -> Paid
A6: COL005 | B6: 46042 | C6: D005 | D6: SP005 | E6: R002 | F6: C002 | G6: 115000 | H6: 46072 | I6: 46071 | J6: 115000 | K6: =G6-J6 -> 0 | L6: =IF(K6=0,"Paid",IF(J6=0,"Outstanding","Partial")) -> Paid
A7: COL006 | B7: 46046 | C7: D006 | D7: SP006 | E7: R002 | F7: C002 | G7: 88000 | H7: 46076 | J7: 0 | K7: =G7-J7 -> 88000 | L7: =IF(K7=0,"Paid",IF(J7=0,"Outstanding","Partial")) -> Outstanding
A8: COL007 | B8: 46050 | C8: D007 | D8: SP007 | E8: R003 | F8: C003 | G8: 97000 | H8: 46080 | I8: 46078 | J8: 97000 | K8: =G8-J8 -> 0 | L8: =IF(K8=0,"Paid",IF(J8=0,"Outstanding","Partial")) -> Paid
A9: COL008 | B9: 46056 | C9: D008 | D9: SP008 | E9: R003 | F9: C003 | G9: 112000 | H9: 46086 | I9: 46084 | J9: 80000 | K9: =G9-J9 -> 32000 | L9: =IF(K9=0,"Paid",IF(J9=0,"Outstanding","Partial")) -> Partial
A10: COL009 | B10: 46060 | C10: D009 | D10: SP009 | E10: R003 | F10: C003 | G10: 89000 | H10: 46090 | I10: 46090 | J10: 89000 | K10: =G10-J10 -> 0 | L10: =IF(K10=0,"Paid",IF(J10=0,"Outstanding","Partial")) -> Paid
A11: COL010 | B11: 46064 | C11: D010 | D11: SP010 | E11: R004 | F11: C004 | G11: 125000 | H11: 46093 | I11: 46091 | J11: 125000 | K11: =G11-J11 -> 0 | L11: =IF(K11=0,"Paid",IF(J11=0,"Outstanding","Partial")) -> Paid
A12: COL011 | B12: 46068 | C12: D011 | D12: SP011 | E12: R004 | F12: C004 | G12: 76000 | H12: 46097 | J12: 0 | K12: =G12-J12 -> 76000 | L12: =IF(K12=0,"Paid",IF(J12=0,"Outstanding","Partial")) -> Outstanding
A13: COL012 | B13: 46073 | C13: D012 | D13: SP012 | E13: R004 | F13: C004 | G13: 108000 | H13: 46102 | I13: 46101 | J13: 90000 | K13: =G13-J13 -> 18000 | L13: =IF(K13=0,"Paid",IF(J13=0,"Outstanding","Partial")) -> Partial
A14: COL013 | B14: 46086 | C14: D001 | D14: SP001 | E14: R001 | F14: C001 | G14: 95000 | H14: 46116 | I14: 46114 | J14: 95000 | K14: =G14-J14 -> 0 | L14: =IF(K14=0,"Paid",IF(J14=0,"Outstanding","Partial")) -> Paid
A15: COL014 | B15: 46091 | C15: D002 | D15: SP002 | E15: R001 | F15: C001 | G15: 118000 | H15: 46121 | I15: 46120 | J15: 118000 | K15: =G15-J15 -> 0 | L15: =IF(K15=0,"Paid",IF(J15=0,"Outstanding","Partial")) -> Paid
A16: COL015 | B16: 46096 | C16: D003 | D16: SP003 | E16: R001 | F16: C001 | G16: 82000 | H16: 46126 | J16: 0 | K16: =G16-J16 -> 82000 | L16: =IF(K16=0,"Paid",IF(J16=0,"Outstanding","Partial")) -> Outstanding
A17: COL016 | B17: 46101 | C17: D004 | D17: SP004 | E17: R002 | F17: C002 | G17: 110000 | H17: 46131 | I17: 46129 | J17: 70000 | K17: =G17-J17 -> 40000 | L17: =IF(K17=0,"Paid",IF(J17=0,"Outstanding","Partial")) -> Partial
A18: COL017 | B18: 46106 | C18: D005 | D18: SP005 | E18: R002 | F18: C002 | G18: 125000 | H18: 46136 | I18: 46136 | J18: 125000 | K18: =G18-J18 -> 0 | L18: =IF(K18=0,"Paid",IF(J18=0,"Outstanding","Partial")) -> Paid
A19: COL018 | B19: 46109 | C19: D006 | D19: SP006 | E19: R002 | F19: C002 | G19: 93000 | H19: 46139 | I19: 46138 | J19: 93000 | K19: =G19-J19 -> 0 | L19: =IF(K19=0,"Paid",IF(J19=0,"Outstanding","Partial")) -> Paid
A20: COL019 | B20: 46114 | C20: D007 | D20: SP007 | E20: R003 | F20: C003 | G20: 102000 | H20: 46144 | I20: 46142 | J20: 102000 | K20: =G20-J20 -> 0 | L20: =IF(K20=0,"Paid",IF(J20=0,"Outstanding","Partial")) -> Paid
A21: COL020 | B21: 46120 | C21: D008 | D21: SP008 | E21: R003 | F21: C003 | G21: 120000 | H21: 46150 | J21: 0 | K21: =G21-J21 -> 120000 | L21: =IF(K21=0,"Paid",IF(J21=0,"Outstanding","Partial")) -> Outstanding
A22: COL021 | B22: 46126 | C22: D009 | D22: SP009 | E22: R003 | F22: C003 | G22: 94000 | H22: 46156 | I22: 46154 | J22: 94000 | K22: =G22-J22 -> 0 | L22: =IF(K22=0,"Paid",IF(J22=0,"Outstanding","Partial")) -> Paid
A23: COL022 | B23: 46132 | C23: D010 | D23: SP010 | E23: R004 | F23: C004 | G23: 135000 | H23: 46162 | I23: 46161 | J23: 135000 | K23: =G23-J23 -> 0 | L23: =IF(K23=0,"Paid",IF(J23=0,"Outstanding","Partial")) -> Paid
A24: COL023 | B24: 46137 | C24: D011 | D24: SP011 | E24: R004 | F24: C004 | G24: 84000 | H24: 46167 | J24: 0 | K24: =G24-J24 -> 84000 | L24: =IF(K24=0,"Paid",IF(J24=0,"Outstanding","Partial")) -> Outstanding
A25: COL024 | B25: 46140 | C25: D012 | D25: SP012 | E25: R004 | F25: C004 | G25: 115000 | H25: 46170 | I25: 46169 | J25: 100000 | K25: =G25-J25 -> 15000 | L25: =IF(K25=0,"Paid",IF(J25=0,"Outstanding","Partial")) -> Partial
A26: COL025 | B26: 46147 | C26: D001 | D26: SP001 | E26: R001 | F26: C001 | G26: 108000 | H26: 46177 | I26: 46176 | J26: 108000 | K26: =G26-J26 -> 0 | L26: =IF(K26=0,"Paid",IF(J26=0,"Outstanding","Partial")) -> Paid
A27: COL026 | B27: 46152 | C27: D002 | D27: SP002 | E27: R001 | F27: C001 | G27: 125000 | H27: 46182 | I27: 46181 | J27: 125000 | K27: =G27-J27 -> 0 | L27: =IF(K27=0,"Paid",IF(J27=0,"Outstanding","Partial")) -> Paid
A28: COL027 | B28: 46157 | C28: D003 | D28: SP003 | E28: R001 | F28: C001 | G28: 90000 | H28: 46187 | J28: 0 | K28: =G28-J28 -> 90000 | L28: =IF(K28=0,"Paid",IF(J28=0,"Outstanding","Partial")) -> Outstanding
A29: COL028 | B29: 46162 | C29: D004 | D29: SP004 | E29: R002 | F29: C002 | G29: 118000 | H29: 46192 | I29: 46191 | J29: 90000 | K29: =G29-J29 -> 28000 | L29: =IF(K29=0,"Paid",IF(J29=0,"Outstanding","Partial")) -> Partial
A30: COL029 | B30: 46167 | C30: D005 | D30: SP005 | E30: R002 | F30: C002 | G30: 132000 | H30: 46197 | I30: 46197 | J30: 132000 | K30: =G30-J30 -> 0 | L30: =IF(K30=0,"Paid",IF(J30=0,"Outstanding","Partial")) -> Paid
A31: COL030 | B31: 46170 | C31: D006 | D31: SP006 | E31: R002 | F31: C002 | G31: 98000 | H31: 46200 | I31: 46199 | J31: 98000 | K31: =G31-J31 -> 0 | L31: =IF(K31=0,"Paid",IF(J31=0,"Outstanding","Partial")) -> Paid
A32: COL031 | B32: 46176 | C32: D007 | D32: SP007 | E32: R003 | F32: C003 | G32: 110000 | H32: 46206 | I32: 46205 | J32: 110000 | K32: =G32-J32 -> 0 | L32: =IF(K32=0,"Paid",IF(J32=0,"Outstanding","Partial")) -> Paid
A33: COL032 | B33: 46181 | C33: D008 | D33: SP008 | E33: R003 | F33: C003 | G33: 128000 | H33: 46211 | J33: 0 | K33: =G33-J33 -> 128000 | L33: =IF(K33=0,"Paid",IF(J33=0,"Outstanding","Partial")) -> Outstanding
A34: COL033 | B34: 46187 | C34: D009 | D34: SP009 | E34: R003 | F34: C003 | G34: 99000 | H34: 46217 | I34: 46215 | J34: 99000 | K34: =G34-J34 -> 0 | L34: =IF(K34=0,"Paid",IF(J34=0,"Outstanding","Partial")) -> Paid
A35: COL034 | B35: 46193 | C35: D010 | D35: SP010 | E35: R004 | F35: C004 | G35: 142000 | H35: 46223 | I35: 46221 | J35: 142000 | K35: =G35-J35 -> 0 | L35: =IF(K35=0,"Paid",IF(J35=0,"Outstanding","Partial")) -> Paid
A36: COL035 | B36: 46198 | C36: D011 | D36: SP011 | E36: R004 | F36: C004 | G36: 91000 | H36: 46228 | J36: 0 | K36: =G36-J36 -> 91000 | L36: =IF(K36=0,"Paid",IF(J36=0,"Outstanding","Partial")) -> Outstanding
A37: COL036 | B37: 46201 | C37: D012 | D37: SP012 | E37: R004 | F37: C004 | G37: 122000 | H37: 46231 | I37: 46230 | J37: 100000 | K37: =G37-J37 -> 22000 | L37: =IF(K37=0,"Paid",IF(J37=0,"Outstanding","Partial")) -> Partial
A38: COL037 | B38: 46208 | C38: D001 | D38: SP001 | E38: R001 | F38: C001 | G38: 115000 | H38: 46238 | I38: 46236 | J38: 115000 | K38: =G38-J38 -> 0 | L38: =IF(K38=0,"Paid",IF(J38=0,"Outstanding","Partial")) -> Paid
A39: COL038 | B39: 46213 | C39: D002 | D39: SP002 | E39: R001 | F39: C001 | G39: 132000 | H39: 46243 | I39: 46242 | J39: 132000 | K39: =G39-J39 -> 0 | L39: =IF(K39=0,"Paid",IF(J39=0,"Outstanding","Partial")) -> Paid
A40: COL039 | B40: 46218 | C40: D003 | D40: SP003 | E40: R001 | F40: C001 | G40: 96000 | H40: 46248 | J40: 0 | K40: =G40-J40 -> 96000 | L40: =IF(K40=0,"Paid",IF(J40=0,"Outstanding","Partial")) -> Outstanding
A41: COL040 | B41: 46223 | C41: D004 | D41: SP004 | E41: R002 | F41: C002 | G41: 125000 | H41: 46253 | I41: 46252 | J41: 95000 | K41: =G41-J41 -> 30000 | L41: =IF(K41=0,"Paid",IF(J41=0,"Outstanding","Partial")) -> Partial
A42: COL041 | B42: 46228 | C42: D005 | D42: SP005 | E42: R002 | F42: C002 | G42: 140000 | H42: 46258 | I42: 46258 | J42: 140000 | K42: =G42-J42 -> 0 | L42: =IF(K42=0,"Paid",IF(J42=0,"Outstanding","Partial")) -> Paid
A43: COL042 | B43: 46231 | C43: D006 | D43: SP006 | E43: R002 | F43: C002 | G43: 105000 | H43: 46261 | I43: 46260 | J43: 105000 | K43: =G43-J43 -> 0 | L43: =IF(K43=0,"Paid",IF(J43=0,"Outstanding","Partial")) -> Paid
A44: COL043 | B44: 46238 | C44: D007 | D44: SP007 | E44: R003 | F44: C003 | G44: 118000 | H44: 46268 | I44: 46267 | J44: 118000 | K44: =G44-J44 -> 0 | L44: =IF(K44=0,"Paid",IF(J44=0,"Outstanding","Partial")) -> Paid
A45: COL044 | B45: 46243 | C45: D008 | D45: SP008 | E45: R003 | F45: C003 | G45: 135000 | H45: 46273 | J45: 0 | K45: =G45-J45 -> 135000 | L45: =IF(K45=0,"Paid",IF(J45=0,"Outstanding","Partial")) -> Outstanding
A46: COL045 | B46: 46249 | C46: D009 | D46: SP009 | E46: R003 | F46: C003 | G46: 102000 | H46: 46279 | I46: 46277 | J46: 102000 | K46: =G46-J46 -> 0 | L46: =IF(K46=0,"Paid",IF(J46=0,"Outstanding","Partial")) -> Paid
A47: COL046 | B47: 46254 | C47: D010 | D47: SP010 | E47: R004 | F47: C004 | G47: 150000 | H47: 46284 | I47: 46283 | J47: 150000 | K47: =G47-J47 -> 0 | L47: =IF(K47=0,"Paid",IF(J47=0,"Outstanding","Partial")) -> Paid
A48: COL047 | B48: 46259 | C48: D011 | D48: SP011 | E48: R004 | F48: C004 | G48: 95000 | H48: 46289 | J48: 0 | K48: =G48-J48 -> 95000 | L48: =IF(K48=0,"Paid",IF(J48=0,"Outstanding","Partial")) -> Outstanding
A49: COL048 | B49: 46262 | C49: D012 | D49: SP012 | E49: R004 | F49: C004 | G49: 130000 | H49: 46292 | I49: 46291 | J49: 110000 | K49: =G49-J49 -> 20000 | L49: =IF(K49=0,"Paid",IF(J49=0,"Outstanding","Partial")) -> Partial
A50: COL049 | B50: 46270 | C50: D001 | D50: SP001 | E50: R001 | F50: C001 | G50: 122000 | H50: 46300 | I50: 46298 | J50: 122000 | K50: =G50-J50 -> 0 | L50: =IF(K50=0,"Paid",IF(J50=0,"Outstanding","Partial")) -> Paid
A51: COL050 | B51: 46275 | C51: D002 | D51: SP002 | E51: R001 | F51: C001 | G51: 140000 | H51: 46305 | I51: 46304 | J51: 140000 | K51: =G51-J51 -> 0 | L51: =IF(K51=0,"Paid",IF(J51=0,"Outstanding","Partial")) -> Paid
A52: COL051 | B52: 46280 | C52: D003 | D52: SP003 | E52: R001 | F52: C001 | G52: 101000 | H52: 46310 | J52: 0 | K52: =G52-J52 -> 101000 | L52: =IF(K52=0,"Paid",IF(J52=0,"Outstanding","Partial")) -> Outstanding
A53: COL052 | B53: 46285 | C53: D004 | D53: SP004 | E53: R002 | F53: C002 | G53: 132000 | H53: 46315 | I53: 46314 | J53: 100000 | K53: =G53-J53 -> 32000 | L53: =IF(K53=0,"Paid",IF(J53=0,"Outstanding","Partial")) -> Partial
A54: COL053 | B54: 46290 | C54: D005 | D54: SP005 | E54: R002 | F54: C002 | G54: 148000 | H54: 46320 | I54: 46320 | J54: 148000 | K54: =G54-J54 -> 0 | L54: =IF(K54=0,"Paid",IF(J54=0,"Outstanding","Partial")) -> Paid
A55: COL054 | B55: 46293 | C55: D006 | D55: SP006 | E55: R002 | F55: C002 | G55: 110000 | H55: 46323 | I55: 46322 | J55: 110000 | K55: =G55-J55 -> 0 | L55: =IF(K55=0,"Paid",IF(J55=0,"Outstanding","Partial")) -> Paid
A56: COL055 | B56: 46300 | C56: D007 | D56: SP007 | E56: R003 | F56: C003 | G56: 125000 | H56: 46330 | I56: 46329 | J56: 125000 | K56: =G56-J56 -> 0 | L56: =IF(K56=0,"Paid",IF(J56=0,"Outstanding","Partial")) -> Paid
A57: COL056 | B57: 46305 | C57: D008 | D57: SP008 | E57: R003 | F57: C003 | G57: 145000 | H57: 46335 | J57: 0 | K57: =G57-J57 -> 145000 | L57: =IF(K57=0,"Paid",IF(J57=0,"Outstanding","Partial")) -> Outstanding
A58: COL057 | B58: 46310 | C58: D009 | D58: SP009 | E58: R003 | F58: C003 | G58: 108000 | H58: 46340 | I58: 46338 | J58: 108000 | K58: =G58-J58 -> 0 | L58: =IF(K58=0,"Paid",IF(J58=0,"Outstanding","Partial")) -> Paid
A59: COL058 | B59: 46315 | C59: D010 | D59: SP010 | E59: R004 | F59: C004 | G59: 158000 | H59: 46345 | I59: 46344 | J59: 158000 | K59: =G59-J59 -> 0 | L59: =IF(K59=0,"Paid",IF(J59=0,"Outstanding","Partial")) -> Paid
A60: COL059 | B60: 46320 | C60: D011 | D60: SP011 | E60: R004 | F60: C004 | G60: 99000 | H60: 46350 | J60: 0 | K60: =G60-J60 -> 99000 | L60: =IF(K60=0,"Paid",IF(J60=0,"Outstanding","Partial")) -> Outstanding
A61: COL060 | B61: 46323 | C61: D012 | D61: SP012 | E61: R004 | F61: C004 | G61: 138000 | H61: 46353 | I61: 46352 | J61: 115000 | K61: =G61-J61 -> 23000 | L61: =IF(K61=0,"Paid",IF(J61=0,"Outstanding","Partial")) -> Partial
A62: COL061 | B62: 46331 | C62: D001 | D62: SP001 | E62: R001 | F62: C001 | G62: 130000 | H62: 46361 | I62: 46359 | J62: 130000 | K62: =G62-J62 -> 0 | L62: =IF(K62=0,"Paid",IF(J62=0,"Outstanding","Partial")) -> Paid
A63: COL062 | B63: 46336 | C63: D002 | D63: SP002 | E63: R001 | F63: C001 | G63: 148000 | H63: 46366 | I63: 46365 | J63: 148000 | K63: =G63-J63 -> 0 | L63: =IF(K63=0,"Paid",IF(J63=0,"Outstanding","Partial")) -> Paid
A64: COL063 | B64: 46341 | C64: D003 | D64: SP003 | E64: R001 | F64: C001 | G64: 105000 | H64: 46371 | J64: 0 | K64: =G64-J64 -> 105000 | L64: =IF(K64=0,"Paid",IF(J64=0,"Outstanding","Partial")) -> Outstanding
A65: COL064 | B65: 46346 | C65: D004 | D65: SP004 | E65: R002 | F65: C002 | G65: 138000 | H65: 46376 | I65: 46375 | J65: 105000 | K65: =G65-J65 -> 33000 | L65: =IF(K65=0,"Paid",IF(J65=0,"Outstanding","Partial")) -> Partial
A66: COL065 | B66: 46351 | C66: D005 | D66: SP005 | E66: R002 | F66: C002 | G66: 155000 | H66: 46381 | I66: 46381 | J66: 155000 | K66: =G66-J66 -> 0 | L66: =IF(K66=0,"Paid",IF(J66=0,"Outstanding","Partial")) -> Paid
A67: COL066 | B67: 46354 | C67: D006 | D67: SP006 | E67: R002 | F67: C002 | G67: 115000 | H67: 46384 | I67: 46383 | J67: 115000 | K67: =G67-J67 -> 0 | L67: =IF(K67=0,"Paid",IF(J67=0,"Outstanding","Partial")) -> Paid
A68: COL067 | B68: 46361 | C68: D007 | D68: SP007 | E68: R003 | F68: C003 | G68: 132000 | H68: 46391 | J68: 0 | K68: =G68-J68 -> 132000 | L68: =IF(K68=0,"Paid",IF(J68=0,"Outstanding","Partial")) -> Outstanding
A69: COL068 | B69: 46366 | C69: D008 | D69: SP008 | E69: R003 | F69: C003 | G69: 152000 | H69: 46396 | J69: 0 | K69: =G69-J69 -> 152000 | L69: =IF(K69=0,"Paid",IF(J69=0,"Outstanding","Partial")) -> Outstanding
A70: COL069 | B70: 46371 | C70: D009 | D70: SP009 | E70: R003 | F70: C003 | G70: 112000 | H70: 46401 | J70: 0 | K70: =G70-J70 -> 112000 | L70: =IF(K70=0,"Paid",IF(J70=0,"Outstanding","Partial")) -> Outstanding
A71: COL070 | B71: 46376 | C71: D010 | D71: SP010 | E71: R004 | F71: C004 | G71: 165000 | H71: 46406 | J71: 0 | K71: =G71-J71 -> 165000 | L71: =IF(K71=0,"Paid",IF(J71=0,"Outstanding","Partial")) -> Outstanding
A72: COL071 | B72: 46381 | C72: D011 | D72: SP011 | E72: R004 | F72: C004 | G72: 102000 | H72: 46411 | J72: 0 | K72: =G72-J72 -> 102000 | L72: =IF(K72=0,"Paid",IF(J72=0,"Outstanding","Partial")) -> Outstanding
A73: COL072 | B73: 46384 | C73: D012 | D73: SP012 | E73: R004 | F73: C004 | G73: 145000 | H73: 46414 | J73: 0 | K73: =G73-J73 -> 145000 | L73: =IF(K73=0,"Paid",IF(J73=0,"Outstanding","Partial")) -> Outstanding

Sheet 12_Performance_Calculations
A1: MonthYear | B1: Month No | C1: Salesperson ID | D1: RSM ID | E1: City ID | F1: Target Amount | G1: Actual Sales | H1: SALES VARIANCE | I1: Achievement % | J1: Performance Status
A2: =DATE(2026,B2,1) -> 46023 | B2: =ROUNDUP(ROWS($B$2:B2)/12,0) -> 1 | C2: ="SP"&TEXT(MOD(ROWS($C$2:C2)-1,12)+1,"000") -> SP001 | D2: R001 | E2: C001 | F2: =SUMIFS(tblSalesTargets[Target Amount],tblSalesTargets[MonthYear],A2,tblSalesTargets[Salesperson ID],C2) -> 2500000 | G2: =SUMIFS(tblSalesTransactions[Sales Amount],tblSalesTransactions[Salesperson ID],C2,tblSalesTransactions[Date],">="&DATE(YEAR(A2),MONTH(A2),1),tblSalesTransactions[Date],"<"&EDATE(A2,1)) -> 350500 | H2: =G2-F2 -> -2149500 | I2: =IFERROR(G2/F2,0) -> 0.1402 | J2: =IF(I2>='02_Control_Panel'!$B$8,"Achieved",IF(I2>='02_Control_Panel'!$B$7,"Near Target","Below Target")) -> Below Target
A3: =DATE(2026,B3,1) -> 46023 | B3: =ROUNDUP(ROWS($B$2:B3)/12,0) -> 1 | C3: ="SP"&TEXT(MOD(ROWS($C$2:C3)-1,12)+1,"000") -> SP002 | D3: R001 | E3: C001 | F3: =SUMIFS(tblSalesTargets[Target Amount],tblSalesTargets[MonthYear],A3,tblSalesTargets[Salesperson ID],C3) -> 2300000 | G3: =SUMIFS(tblSalesTransactions[Sales Amount],tblSalesTransactions[Salesperson ID],C3,tblSalesTransactions[Date],">="&DATE(YEAR(A3),MONTH(A3),1),tblSalesTransactions[Date],"<"&EDATE(A3,1)) -> 375000 | H3: =G3-F3 -> -1925000 | I3: =IFERROR(G3/F3,0) -> 0.16304348 | J3: =IF(I3>='02_Control_Panel'!$B$8,"Achieved",IF(I3>='02_Control_Panel'!$B$7,"Near Target","Below Target")) -> Below Target
A4: =DATE(2026,B4,1) -> 46023 | B4: =ROUNDUP(ROWS($B$2:B4)/12,0) -> 1 | C4: ="SP"&TEXT(MOD(ROWS($C$2:C4)-1,12)+1,"000") -> SP003 | D4: R001 | E4: C001 | F4: =SUMIFS(tblSalesTargets[Target Amount],tblSalesTargets[MonthYear],A4,tblSalesTargets[Salesperson ID],C4) -> 2200000 | G4: =SUMIFS(tblSalesTransactions[Sales Amount],tblSalesTransactions[Salesperson ID],C4,tblSalesTransactions[Date],">="&DATE(YEAR(A4),MONTH(A4),1),tblSalesTransactions[Date],"<"&EDATE(A4,1)) -> 371750 | H4: =G4-F4 -> -1828250 | I4: =IFERROR(G4/F4,0) -> 0.16897727 | J4: =IF(I4>='02_Control_Panel'!$B$8,"Achieved",IF(I4>='02_Control_Panel'!$B$7,"Near Target","Below Target")) -> Below Target
A5: =DATE(2026,B5,1) -> 46023 | B5: =ROUNDUP(ROWS($B$2:B5)/12,0) -> 1 | C5: ="SP"&TEXT(MOD(ROWS($C$2:C5)-1,12)+1,"000") -> SP004 | D5: R002 | E5: C002 | F5: =SUMIFS(tblSalesTargets[Target Amount],tblSalesTargets[MonthYear],A5,tblSalesTargets[Salesperson ID],C5) -> 2700000 | G5: =SUMIFS(tblSalesTransactions[Sales Amount],tblSalesTransactions[Salesperson ID],C5,tblSalesTransactions[Date],">="&DATE(YEAR(A5),MONTH(A5),1),tblSalesTransactions[Date],"<"&EDATE(A5,1)) -> 648000 | H5: =G5-F5 -> -2052000 | I5: =IFERROR(G5/F5,0) -> 0.24 | J5: =IF(I5>='02_Control_Panel'!$B$8,"Achieved",IF(I5>='02_Control_Panel'!$B$7,"Near Target","Below Target")) -> Below Target
A6: =DATE(2026,B6,1) -> 46023 | B6: =ROUNDUP(ROWS($B$2:B6)/12,0) -> 1 | C6: ="SP"&TEXT(MOD(ROWS($C$2:C6)-1,12)+1,"000") -> SP005 | D6: R002 | E6: C002 | F6: =SUMIFS(tblSalesTargets[Target Amount],tblSalesTargets[MonthYear],A6,tblSalesTargets[Salesperson ID],C6) -> 2500000 | G6: =SUMIFS(tblSalesTransactions[Sales Amount],tblSalesTransactions[Salesperson ID],C6,tblSalesTransactions[Date],">="&DATE(YEAR(A6),MONTH(A6),1),tblSalesTransactions[Date],"<"&EDATE(A6,1)) -> 626000 | H6: =G6-F6 -> -1874000 | I6: =IFERROR(G6/F6,0) -> 0.2504 | J6: =IF(I6>='02_Control_Panel'!$B$8,"Achieved",IF(I6>='02_Control_Panel'!$B$7,"Near Target","Below Target")) -> Below Target
A7: =DATE(2026,B7,1) -> 46023 | B7: =ROUNDUP(ROWS($B$2:B7)/12,0) -> 1 | C7: ="SP"&TEXT(MOD(ROWS($C$2:C7)-1,12)+1,"000") -> SP006 | D7: R002 | E7: C002 | F7: =SUMIFS(tblSalesTargets[Target Amount],tblSalesTargets[MonthYear],A7,tblSalesTargets[Salesperson ID],C7) -> 2300000 | G7: =SUMIFS(tblSalesTransactions[Sales Amount],tblSalesTransactions[Salesperson ID],C7,tblSalesTransactions[Date],">="&DATE(YEAR(A7),MONTH(A7),1),tblSalesTransactions[Date],"<"&EDATE(A7,1)) -> 464500 | H7: =G7-F7 -> -1835500 | I7: =IFERROR(G7/F7,0) -> 0.20195652 | J7: =IF(I7>='02_Control_Panel'!$B$8,"Achieved",IF(I7>='02_Control_Panel'!$B$7,"Near Target","Below Target")) -> Below Target
A8: =DATE(2026,B8,1) -> 46023 | B8: =ROUNDUP(ROWS($B$2:B8)/12,0) -> 1 | C8: ="SP"&TEXT(MOD(ROWS($C$2:C8)-1,12)+1,"000") -> SP007 | D8: R003 | E8: C003 | F8: =SUMIFS(tblSalesTargets[Target Amount],tblSalesTargets[MonthYear],A8,tblSalesTargets[Salesperson ID],C8) -> 2400000 | G8: =SUMIFS(tblSalesTransactions[Sales Amount],tblSalesTransactions[Salesperson ID],C8,tblSalesTransactions[Date],">="&DATE(YEAR(A8),MONTH(A8),1),tblSalesTransactions[Date],"<"&EDATE(A8,1)) -> 638000 | H8: =G8-F8 -> -1762000 | I8: =IFERROR(G8/F8,0) -> 0.26583333 | J8: =IF(I8>='02_Control_Panel'!$B$8,"Achieved",IF(I8>='02_Control_Panel'!$B$7,"Near Target","Below Target")) -> Below Target
A9: =DATE(2026,B9,1) -> 46023 | B9: =ROUNDUP(ROWS($B$2:B9)/12,0) -> 1 | C9: ="SP"&TEXT(MOD(ROWS($C$2:C9)-1,12)+1,"000") -> SP008 | D9: R003 | E9: C003 | F9: =SUMIFS(tblSalesTargets[Target Amount],tblSalesTargets[MonthYear],A9,tblSalesTargets[Salesperson ID],C9) -> 2200000 | G9: =SUMIFS(tblSalesTransactions[Sales Amount],tblSalesTransactions[Salesperson ID],C9,tblSalesTransactions[Date],">="&DATE(YEAR(A9),MONTH(A9),1),tblSalesTransactions[Date],"<"&EDATE(A9,1)) -> 591000 | H9: =G9-F9 -> -1609000 | I9: =IFERROR(G9/F9,0) -> 0.26863636 | J9: =IF(I9>='02_Control_Panel'!$B$8,"Achieved",IF(I9>='02_Control_Panel'!$B$7,"Near Target","Below Target")) -> Below Target
A10: =DATE(2026,B10,1) -> 46023 | B10: =ROUNDUP(ROWS($B$2:B10)/12,0) -> 1 | C10: ="SP"&TEXT(MOD(ROWS($C$2:C10)-1,12)+1,"000") -> SP009 | D10: R003 | E10: C003 | F10: =SUMIFS(tblSalesTargets[Target Amount],tblSalesTargets[MonthYear],A10,tblSalesTargets[Salesperson ID],C10) -> 2100000 | G10: =SUMIFS(tblSalesTransactions[Sales Amount],tblSalesTransactions[Salesperson ID],C10,tblSalesTransactions[Date],">="&DATE(YEAR(A10),MONTH(A10),1),tblSalesTransactions[Date],"<"&EDATE(A10,1)) -> 456000 | H10: =G10-F10 -> -1644000 | I10: =IFERROR(G10/F10,0) -> 0.21714286 | J10: =IF(I10>='02_Control_Panel'!$B$8,"Achieved",IF(I10>='02_Control_Panel'!$B$7,"Near Target","Below Target")) -> Below Target
A11: =DATE(2026,B11,1) -> 46023 | B11: =ROUNDUP(ROWS($B$2:B11)/12,0) -> 1 | C11: ="SP"&TEXT(MOD(ROWS($C$2:C11)-1,12)+1,"000") -> SP010 | D11: R004 | E11: C004 | F11: =SUMIFS(tblSalesTargets[Target Amount],tblSalesTargets[MonthYear],A11,tblSalesTargets[Salesperson ID],C11) -> 2200000 | G11: =SUMIFS(tblSalesTransactions[Sales Amount],tblSalesTransactions[Salesperson ID],C11,tblSalesTransactions[Date],">="&DATE(YEAR(A11),MONTH(A11),1),tblSalesTransactions[Date],"<"&EDATE(A11,1)) -> 379500 | H11: =G11-F11 -> -1820500 | I11: =IFERROR(G11/F11,0) -> 0.1725 | J11: =IF(I11>='02_Control_Panel'!$B$8,"Achieved",IF(I11>='02_Control_Panel'!$B$7,"Near Target","Below Target")) -> Below Target
A12: =DATE(2026,B12,1) -> 46023 | B12: =ROUNDUP(ROWS($B$2:B12)/12,0) -> 1 | C12: ="SP"&TEXT(MOD(ROWS($C$2:C12)-1,12)+1,"000") -> SP011 | D12: R004 | E12: C004 | F12: =SUMIFS(tblSalesTargets[Target Amount],tblSalesTargets[MonthYear],A12,tblSalesTargets[Salesperson ID],C12) -> 2000000 | G12: =SUMIFS(tblSalesTransactions[Sales Amount],tblSalesTransactions[Salesperson ID],C12,tblSalesTransactions[Date],">="&DATE(YEAR(A12),MONTH(A12),1),tblSalesTransactions[Date],"<"&EDATE(A12,1)) -> 387000 | H12: =G12-F12 -> -1613000 | I12: =IFERROR(G12/F12,0) -> 0.1935 | J12: =IF(I12>='02_Control_Panel'!$B$8,"Achieved",IF(I12>='02_Control_Panel'!$B$7,"Near Target","Below Target")) -> Below Target
A13: =DATE(2026,B13,1) -> 46023 | B13: =ROUNDUP(ROWS($B$2:B13)/12,0) -> 1 | C13: ="SP"&TEXT(MOD(ROWS($C$2:C13)-1,12)+1,"000") -> SP012 | D13: R004 | E13: C004 | F13: =SUMIFS(tblSalesTargets[Target Amount],tblSalesTargets[MonthYear],A13,tblSalesTargets[Salesperson ID],C13) -> 1900000 | G13: =SUMIFS(tblSalesTransactions[Sales Amount],tblSalesTransactions[Salesperson ID],C13,tblSalesTransactions[Date],">="&DATE(YEAR(A13),MONTH(A13),1),tblSalesTransactions[Date],"<"&EDATE(A13,1)) -> 404000 | H13: =G13-F13 -> -1496000 | I13: =IFERROR(G13/F13,0) -> 0.21263158 | J13: =IF(I13>='02_Control_Panel'!$B$8,"Achieved",IF(I13>='02_Control_Panel'!$B$7,"Near Target","Below Target")) -> Below Target
... A145: =DATE(2026,B145,1) -> 46357 | B145: =ROUNDUP(ROWS($B$2:B145)/12,0) -> 12 | C145: ="SP"&TEXT(MOD(ROWS($C$2:C145)-1,12)+1,"000") -> SP012 | D145: R004 | E145: C004 | F145: =SUMIFS(tblSalesTargets[Target Amount],tblSalesTargets[MonthYear],A145,tblSalesTargets[Salesperson ID],C145) -> 2280000 | G145: =SUMIFS(tblSalesTransactions[Sales Amount],tblSalesTransactions[Salesperson ID],C145,tblSalesTransactions[Date],">="&DATE(YEAR(A145),MONTH(A145),1),tblSalesTransactions[Date],"<"&EDATE(A145,1)) -> 415250 | H145: =G145-F145 -> -1864750 | I145: =IFERROR(G145/F145,0) -> 0.18212719 | J145: =IF(I145>='02_Control_Panel'!$B$8,"Achieved",IF(I145>='02_Control_Panel'!$B$7,"Near Target","Below Target")) -> Below Target
F146: =SUBTOTAL(109,tblPerformance[Target Amount]) -> 348075000 | G146: =SUBTOTAL(109,tblPerformance[Actual Sales]) -> 60255750 | H146: =SUBTOTAL(109,tblPerformance[SALES VARIANCE]) -> -287819250 | I146: =IFERROR(SUM(tblPerformance[Actual Sales])/SUM(tblPerformance[Target Amount]),0) -> 0.1731114

Sheet 13_Target_vs_Actual
A1: Target vs Actual Performance
A3: MonthYear | B3: Month No | C3: Salesperson ID | D3: RSM ID | E3: City ID | F3: Target Amount | G3: Actual Sales | H3: SALES VARIANCE | I3: Achievement % | J3: Performance Status | M3: Overall KPI | S3: 1 | T3: 2 | U3: 3 | V3: 4 | W3: 5 | X3: 6
A4: 46023 | B4: 1 | C4: SP001 | D4: R001 | E4: C001 | F4: =SUMIFS(tblSalesTargets[Target Amount],tblSalesTargets[MonthYear],A4,tblSalesTargets[Salesperson ID],C4) -> 2500000 | G4: =SUMIFS(tblSalesTransactions[Sales Amount],tblSalesTransactions[Salesperson ID],C4,tblSalesTransactions[Date],">="&A4,tblSalesTransactions[Date],"<"&EDATE(A4,1)) -> 350500 | H4: =G4-F4 -> -2149500 | I4: =IFERROR(G4/F4,0) -> 0.1402 | J4: =IF(I4>=1,"Achieved",IF(I4>=0.9,"Near Target","Below Target")) -> Below Target | M4: Total Target | N4: =SUM(tblTargetVsActual[Target Amount]) -> 348075000 | S4: =SUMIFS(tblSalesTargets[Target Amount],tblSalesTargets[MonthYear],A4,tblSalesTargets[Salesperson ID],C4) -> 2500000 | T4: =SUMIFS(tblSalesTransactions[Sales Amount],tblSalesTransactions[Salesperson ID],C4,tblSalesTransactions[Date],">="&A4,tblSalesTransactions[Date],"<"&EDATE(A4,1)) -> 350500 | U4: =F4 -> 2500000 | V4: =G4 -> 350500 | W4: =S4=U4 -> TRUE | X4: =T4=V4 -> TRUE
A5: 46023 | B5: 1 | C5: SP002 | D5: R001 | E5: C001 | F5: =SUMIFS(tblSalesTargets[Target Amount],tblSalesTargets[MonthYear],A5,tblSalesTargets[Salesperson ID],C5) -> 2300000 | G5: =SUMIFS(tblSalesTransactions[Sales Amount],tblSalesTransactions[Salesperson ID],C5,tblSalesTransactions[Date],">="&A5,tblSalesTransactions[Date],"<"&EDATE(A5,1)) -> 375000 | H5: =G5-F5 -> -1925000 | I5: =IFERROR(G5/F5,0) -> 0.16304348 | J5: =IF(I5>=1,"Achieved",IF(I5>=0.9,"Near Target","Below Target")) -> Below Target | M5: Total Actual Sales | N5: =SUM(tblTargetVsActual[Actual Sales]) -> 60255750 | S5: =SUMIFS(tblSalesTargets[Target Amount],tblSalesTargets[MonthYear],A5,tblSalesTargets[Salesperson ID],C5) -> 2300000 | T5: =SUMIFS(tblSalesTransactions[Sales Amount],tblSalesTransactions[Salesperson ID],C5,tblSalesTransactions[Date],">="&A5,tblSalesTransactions[Date],"<"&EDATE(A5,1)) -> 375000 | U5: =F5 -> 2300000 | V5: =G5 -> 375000 | W5: =S5=U5 -> TRUE | X5: =T5=V5 -> TRUE
A6: 46023 | B6: 1 | C6: SP003 | D6: R001 | E6: C001 | F6: =SUMIFS(tblSalesTargets[Target Amount],tblSalesTargets[MonthYear],A6,tblSalesTargets[Salesperson ID],C6) -> 2200000 | G6: =SUMIFS(tblSalesTransactions[Sales Amount],tblSalesTransactions[Salesperson ID],C6,tblSalesTransactions[Date],">="&A6,tblSalesTransactions[Date],"<"&EDATE(A6,1)) -> 371750 | H6: =G6-F6 -> -1828250 | I6: =IFERROR(G6/F6,0) -> 0.16897727 | J6: =IF(I6>=1,"Achieved",IF(I6>=0.9,"Near Target","Below Target")) -> Below Target | M6: Total Variance | N6: =N5-N4 -> -287819250 | S6: =SUMIFS(tblSalesTargets[Target Amount],tblSalesTargets[MonthYear],A6,tblSalesTargets[Salesperson ID],C6) -> 2200000 | T6: =SUMIFS(tblSalesTransactions[Sales Amount],tblSalesTransactions[Salesperson ID],C6,tblSalesTransactions[Date],">="&A6,tblSalesTransactions[Date],"<"&EDATE(A6,1)) -> 371750 | U6: =F6 -> 2200000 | V6: =G6 -> 371750 | W6: =S6=U6 -> TRUE | X6: =T6=V6 -> TRUE
A7: 46023 | B7: 1 | C7: SP004 | D7: R002 | E7: C002 | F7: =SUMIFS(tblSalesTargets[Target Amount],tblSalesTargets[MonthYear],A7,tblSalesTargets[Salesperson ID],C7) -> 2700000 | G7: =SUMIFS(tblSalesTransactions[Sales Amount],tblSalesTransactions[Salesperson ID],C7,tblSalesTransactions[Date],">="&A7,tblSalesTransactions[Date],"<"&EDATE(A7,1)) -> 648000 | H7: =G7-F7 -> -2052000 | I7: =IFERROR(G7/F7,0) -> 0.24 | J7: =IF(I7>=1,"Achieved",IF(I7>=0.9,"Near Target","Below Target")) -> Below Target | M7: Overall Achievement % | N7: =IFERROR(N5/N4,0) -> 0.1731114 | S7: =SUMIFS(tblSalesTargets[Target Amount],tblSalesTargets[MonthYear],A7,tblSalesTargets[Salesperson ID],C7) -> 2700000 | T7: =SUMIFS(tblSalesTransactions[Sales Amount],tblSalesTransactions[Salesperson ID],C7,tblSalesTransactions[Date],">="&A7,tblSalesTransactions[Date],"<"&EDATE(A7,1)) -> 648000 | U7: =F7 -> 2700000 | V7: =G7 -> 648000 | W7: =S7=U7 -> TRUE | X7: =T7=V7 -> TRUE
A8: 46023 | B8: 1 | C8: SP005 | D8: R002 | E8: C002 | F8: =SUMIFS(tblSalesTargets[Target Amount],tblSalesTargets[MonthYear],A8,tblSalesTargets[Salesperson ID],C8) -> 2500000 | G8: =SUMIFS(tblSalesTransactions[Sales Amount],tblSalesTransactions[Salesperson ID],C8,tblSalesTransactions[Date],">="&A8,tblSalesTransactions[Date],"<"&EDATE(A8,1)) -> 626000 | H8: =G8-F8 -> -1874000 | I8: =IFERROR(G8/F8,0) -> 0.2504 | J8: =IF(I8>=1,"Achieved",IF(I8>=0.9,"Near Target","Below Target")) -> Below Target | S8: =SUMIFS(tblSalesTargets[Target Amount],tblSalesTargets[MonthYear],A8,tblSalesTargets[Salesperson ID],C8) -> 2500000 | T8: =SUMIFS(tblSalesTransactions[Sales Amount],tblSalesTransactions[Salesperson ID],C8,tblSalesTransactions[Date],">="&A8,tblSalesTransactions[Date],"<"&EDATE(A8,1)) -> 626000 | U8: =F8 -> 2500000 | V8: =G8 -> 626000 | W8: =S8=U8 -> TRUE | X8: =T8=V8 -> TRUE
A9: 46023 | B9: 1 | C9: SP006 | D9: R002 | E9: C002 | F9: =SUMIFS(tblSalesTargets[Target Amount],tblSalesTargets[MonthYear],A9,tblSalesTargets[Salesperson ID],C9) -> 2300000 | G9: =SUMIFS(tblSalesTransactions[Sales Amount],tblSalesTransactions[Salesperson ID],C9,tblSalesTransactions[Date],">="&A9,tblSalesTransactions[Date],"<"&EDATE(A9,1)) -> 464500 | H9: =G9-F9 -> -1835500 | I9: =IFERROR(G9/F9,0) -> 0.20195652 | J9: =IF(I9>=1,"Achieved",IF(I9>=0.9,"Near Target","Below Target")) -> Below Target | S9: =SUMIFS(tblSalesTargets[Target Amount],tblSalesTargets[MonthYear],A9,tblSalesTargets[Salesperson ID],C9) -> 2300000 | T9: =SUMIFS(tblSalesTransactions[Sales Amount],tblSalesTransactions[Salesperson ID],C9,tblSalesTransactions[Date],">="&A9,tblSalesTransactions[Date],"<"&EDATE(A9,1)) -> 464500 | U9: =F9 -> 2300000 | V9: =G9 -> 464500 | W9: =S9=U9 -> TRUE | X9: =T9=V9 -> TRUE
A10: 46023 | B10: 1 | C10: SP007 | D10: R003 | E10: C003 | F10: =SUMIFS(tblSalesTargets[Target Amount],tblSalesTargets[MonthYear],A10,tblSalesTargets[Salesperson ID],C10) -> 2400000 | G10: =SUMIFS(tblSalesTransactions[Sales Amount],tblSalesTransactions[Salesperson ID],C10,tblSalesTransactions[Date],">="&A10,tblSalesTransactions[Date],"<"&EDATE(A10,1)) -> 638000 | H10: =G10-F10 -> -1762000 | I10: =IFERROR(G10/F10,0) -> 0.26583333 | J10: =IF(I10>=1,"Achieved",IF(I10>=0.9,"Near Target","Below Target")) -> Below Target | M10: MonthYear | N10: Target | O10: Actual Sales | P10: SALES Variance | Q10: Achievement % | S10: =SUMIFS(tblSalesTargets[Target Amount],tblSalesTargets[MonthYear],A10,tblSalesTargets[Salesperson ID],C10) -> 2400000 | T10: =SUMIFS(tblSalesTransactions[Sales Amount],tblSalesTransactions[Salesperson ID],C10,tblSalesTransactions[Date],">="&A10,tblSalesTransactions[Date],"<"&EDATE(A10,1)) -> 638000 | U10: =F10 -> 2400000 | V10: =G10 -> 638000 | W10: =S10=U10 -> TRUE | X10: =T10=V10 -> TRUE
A11: 46023 | B11: 1 | C11: SP008 | D11: R003 | E11: C003 | F11: =SUMIFS(tblSalesTargets[Target Amount],tblSalesTargets[MonthYear],A11,tblSalesTargets[Salesperson ID],C11) -> 2200000 | G11: =SUMIFS(tblSalesTransactions[Sales Amount],tblSalesTransactions[Salesperson ID],C11,tblSalesTransactions[Date],">="&A11,tblSalesTransactions[Date],"<"&EDATE(A11,1)) -> 591000 | H11: =G11-F11 -> -1609000 | I11: =IFERROR(G11/F11,0) -> 0.26863636 | J11: =IF(I11>=1,"Achieved",IF(I11>=0.9,"Near Target","Below Target")) -> Below Target | M11: =DATE(2026,1,1) -> 46023 | N11: =SUMIFS(tblTargetVsActual[Target Amount],tblTargetVsActual[MonthYear],M11) -> 27300000 | O11: =SUMIFS(tblTargetVsActual[Actual Sales],tblTargetVsActual[MonthYear],M11) -> 5691250 | P11: =O11-N11 -> -21608750 | Q11: =IFERROR(O11/N11,0) -> 0.2084707 | S11: =SUMIFS(tblSalesTargets[Target Amount],tblSalesTargets[MonthYear],A11,tblSalesTargets[Salesperson ID],C11) -> 2200000 | T11: =SUMIFS(tblSalesTransactions[Sales Amount],tblSalesTransactions[Salesperson ID],C11,tblSalesTransactions[Date],">="&A11,tblSalesTransactions[Date],"<"&EDATE(A11,1)) -> 591000 | U11: =F11 -> 2200000 | V11: =G11 -> 591000 | W11: =S11=U11 -> TRUE | X11: =T11=V11 -> TRUE
A12: 46023 | B12: 1 | C12: SP009 | D12: R003 | E12: C003 | F12: =SUMIFS(tblSalesTargets[Target Amount],tblSalesTargets[MonthYear],A12,tblSalesTargets[Salesperson ID],C12) -> 2100000 | G12: =SUMIFS(tblSalesTransactions[Sales Amount],tblSalesTransactions[Salesperson ID],C12,tblSalesTransactions[Date],">="&A12,tblSalesTransactions[Date],"<"&EDATE(A12,1)) -> 456000 | H12: =G12-F12 -> -1644000 | I12: =IFERROR(G12/F12,0) -> 0.21714286 | J12: =IF(I12>=1,"Achieved",IF(I12>=0.9,"Near Target","Below Target")) -> Below Target | M12: =EDATE(M11,1) -> 46054 | N12: =SUMIFS(tblTargetVsActual[Target Amount],tblTargetVsActual[MonthYear],M12) -> 28119000 | O12: =SUMIFS(tblTargetVsActual[Actual Sales],tblTargetVsActual[MonthYear],M12) -> 4273750 | P12: =O12-N12 -> -23845250 | Q12: =IFERROR(O12/N12,0) -> 0.15198798 | S12: =SUMIFS(tblSalesTargets[Target Amount],tblSalesTargets[MonthYear],A12,tblSalesTargets[Salesperson ID],C12) -> 2100000 | T12: =SUMIFS(tblSalesTransactions[Sales Amount],tblSalesTransactions[Salesperson ID],C12,tblSalesTransactions[Date],">="&A12,tblSalesTransactions[Date],"<"&EDATE(A12,1)) -> 456000 | U12: =F12 -> 2100000 | V12: =G12 -> 456000 | W12: =S12=U12 -> TRUE | X12: =T12=V12 -> TRUE
A13: 46023 | B13: 1 | C13: SP010 | D13: R004 | E13: C004 | F13: =SUMIFS(tblSalesTargets[Target Amount],tblSalesTargets[MonthYear],A13,tblSalesTargets[Salesperson ID],C13) -> 2200000 | G13: =SUMIFS(tblSalesTransactions[Sales Amount],tblSalesTransactions[Salesperson ID],C13,tblSalesTransactions[Date],">="&A13,tblSalesTransactions[Date],"<"&EDATE(A13,1)) -> 379500 | H13: =G13-F13 -> -1820500 | I13: =IFERROR(G13/F13,0) -> 0.1725 | J13: =IF(I13>=1,"Achieved",IF(I13>=0.9,"Near Target","Below Target")) -> Below Target | M13: =EDATE(M12,1) -> 46082 | N13: =SUMIFS(tblTargetVsActual[Target Amount],tblTargetVsActual[MonthYear],M13) -> 28665000 | O13: =SUMIFS(tblTargetVsActual[Actual Sales],tblTargetVsActual[MonthYear],M13) -> 4507750 | P13: =O13-N13 -> -24157250 | Q13: =IFERROR(O13/N13,0) -> 0.15725624 | S13: =SUMIFS(tblSalesTargets[Target Amount],tblSalesTargets[MonthYear],A13,tblSalesTargets[Salesperson ID],C13) -> 2200000 | T13: =SUMIFS(tblSalesTransactions[Sales Amount],tblSalesTransactions[Salesperson ID],C13,tblSalesTransactions[Date],">="&A13,tblSalesTransactions[Date],"<"&EDATE(A13,1)) -> 379500 | U13: =F13 -> 2200000 | V13: =G13 -> 379500 | W13: =S13=U13 -> TRUE | X13: =T13=V13 -> TRUE
A14: 46023 | B14: 1 | C14: SP011 | D14: R004 | E14: C004 | F14: =SUMIFS(tblSalesTargets[Target Amount],tblSalesTargets[MonthYear],A14,tblSalesTargets[Salesperson ID],C14) -> 2000000 | G14: =SUMIFS(tblSalesTransactions[Sales Amount],tblSalesTransactions[Salesperson ID],C14,tblSalesTransactions[Date],">="&A14,tblSalesTransactions[Date],"<"&EDATE(A14,1)) -> 387000 | H14: =G14-F14 -> -1613000 | I14: =IFERROR(G14/F14,0) -> 0.1935 | J14: =IF(I14>=1,"Achieved",IF(I14>=0.9,"Near Target","Below Target")) -> Below Target | M14: =EDATE(M13,1) -> 46113 | N14: =SUMIFS(tblTargetVsActual[Target Amount],tblTargetVsActual[MonthYear],M14) -> 26754000 | O14: =SUMIFS(tblTargetVsActual[Actual Sales],tblTargetVsActual[MonthYear],M14) -> 3900000 | P14: =O14-N14 -> -22854000 | Q14: =IFERROR(O14/N14,0) -> 0.14577259 | S14: =SUMIFS(tblSalesTargets[Target Amount],tblSalesTargets[MonthYear],A14,tblSalesTargets[Salesperson ID],C14) -> 2000000 | T14: =SUMIFS(tblSalesTransactions[Sales Amount],tblSalesTransactions[Salesperson ID],C14,tblSalesTransactions[Date],">="&A14,tblSalesTransactions[Date],"<"&EDATE(A14,1)) -> 387000 | U14: =F14 -> 2000000 | V14: =G14 -> 387000 | W14: =S14=U14 -> TRUE | X14: =T14=V14 -> TRUE
A15: 46023 | B15: 1 | C15: SP012 | D15: R004 | E15: C004 | F15: =SUMIFS(tblSalesTargets[Target Amount],tblSalesTargets[MonthYear],A15,tblSalesTargets[Salesperson ID],C15) -> 1900000 | G15: =SUMIFS(tblSalesTransactions[Sales Amount],tblSalesTransactions[Salesperson ID],C15,tblSalesTransactions[Date],">="&A15,tblSalesTransactions[Date],"<"&EDATE(A15,1)) -> 404000 | H15: =G15-F15 -> -1496000 | I15: =IFERROR(G15/F15,0) -> 0.21263158 | J15: =IF(I15>=1,"Achieved",IF(I15>=0.9,"Near Target","Below Target")) -> Below Target | M15: =EDATE(M14,1) -> 46143 | N15: =SUMIFS(tblTargetVsActual[Target Amount],tblTargetVsActual[MonthYear],M15) -> 27846000 | O15: =SUMIFS(tblTargetVsActual[Actual Sales],tblTargetVsActual[MonthYear],M15) -> 4602250 | P15: =O15-N15 -> -23243750 | Q15: =IFERROR(O15/N15,0) -> 0.16527508 | S15: =SUMIFS(tblSalesTargets[Target Amount],tblSalesTargets[MonthYear],A15,tblSalesTargets[Salesperson ID],C15) -> 1900000 | T15: =SUMIFS(tblSalesTransactions[Sales Amount],tblSalesTransactions[Salesperson ID],C15,tblSalesTransactions[Date],">="&A15,tblSalesTransactions[Date],"<"&EDATE(A15,1)) -> 404000 | U15: =F15 -> 1900000 | V15: =G15 -> 404000 | W15: =S15=U15 -> TRUE | X15: =T15=V15 -> TRUE
A16: 46054 | B16: 2 | C16: SP001 | D16: R001 | E16: C001 | F16: =SUMIFS(tblSalesTargets[Target Amount],tblSalesTargets[MonthYear],A16,tblSalesTargets[Salesperson ID],C16) -> 2575000 | G16: =SUMIFS(tblSalesTransactions[Sales Amount],tblSalesTransactions[Salesperson ID],C16,tblSalesTransactions[Date],">="&A16,tblSalesTransactions[Date],"<"&EDATE(A16,1)) -> 236500 | H16: =G16-F16 -> -2338500 | I16: =IFERROR(G16/F16,0) -> 0.09184466 | J16: =IF(I16>=1,"Achieved",IF(I16>=0.9,"Near Target","Below Target")) -> Below Target | M16: =EDATE(M15,1) -> 46174 | N16: =SUMIFS(tblTargetVsActual[Target Amount],tblTargetVsActual[MonthYear],M16) -> 29484000 | O16: =SUMIFS(tblTargetVsActual[Actual Sales],tblTargetVsActual[MonthYear],M16) -> 4729000 | P16: =O16-N16 -> -24755000 | Q16: =IFERROR(O16/N16,0) -> 0.16039208 | S16: =SUMIFS(tblSalesTargets[Target Amount],tblSalesTargets[MonthYear],A16,tblSalesTargets[Salesperson ID],C16) -> 2575000 | T16: =SUMIFS(tblSalesTransactions[Sales Amount],tblSalesTransactions[Salesperson ID],C16,tblSalesTransactions[Date],">="&A16,tblSalesTransactions[Date],"<"&EDATE(A16,1)) -> 236500 | U16: =F16 -> 2575000 | V16: =G16 -> 236500 | W16: =S16=U16 -> TRUE | X16: =T16=V16 -> TRUE
A17: 46054 | B17: 2 | C17: SP002 | D17: R001 | E17: C001 | F17: =SUMIFS(tblSalesTargets[Target Amount],tblSalesTargets[MonthYear],A17,tblSalesTargets[Salesperson ID],C17) -> 2369000 | G17: =SUMIFS(tblSalesTransactions[Sales Amount],tblSalesTransactions[Salesperson ID],C17,tblSalesTransactions[Date],">="&A17,tblSalesTransactions[Date],"<"&EDATE(A17,1)) -> 303500 | H17: =G17-F17 -> -2065500 | I17: =IFERROR(G17/F17,0) -> 0.12811313 | J17: =IF(I17>=1,"Achieved",IF(I17>=0.9,"Near Target","Below Target")) -> Below Target | M17: =EDATE(M16,1) -> 46204 | N17: =SUMIFS(tblTargetVsActual[Target Amount],tblTargetVsActual[MonthYear],M17) -> 28392000 | O17: =SUMIFS(tblTargetVsActual[Actual Sales],tblTargetVsActual[MonthYear],M17) -> 4432750 | P17: =O17-N17 -> -23959250 | Q17: =IFERROR(O17/N17,0) -> 0.15612673 | S17: =SUMIFS(tblSalesTargets[Target Amount],tblSalesTargets[MonthYear],A17,tblSalesTargets[Salesperson ID],C17) -> 2369000 | T17: =SUMIFS(tblSalesTransactions[Sales Amount],tblSalesTransactions[Salesperson ID],C17,tblSalesTransactions[Date],">="&A17,tblSalesTransactions[Date],"<"&EDATE(A17,1)) -> 303500 | U17: =F17 -> 2369000 | V17: =G17 -> 303500 | W17: =S17=U17 -> TRUE | X17: =T17=V17 -> TRUE
A18: 46054 | B18: 2 | C18: SP003 | D18: R001 | E18: C001 | F18: =SUMIFS(tblSalesTargets[Target Amount],tblSalesTargets[MonthYear],A18,tblSalesTargets[Salesperson ID],C18) -> 2266000 | G18: =SUMIFS(tblSalesTransactions[Sales Amount],tblSalesTransactions[Salesperson ID],C18,tblSalesTransactions[Date],">="&A18,tblSalesTransactions[Date],"<"&EDATE(A18,1)) -> 287250 | H18: =G18-F18 -> -1978750 | I18: =IFERROR(G18/F18,0) -> 0.12676523 | J18: =IF(I18>=1,"Achieved",IF(I18>=0.9,"Near Target","Below Target")) -> Below Target | M18: =EDATE(M17,1) -> 46235 | N18: =SUMIFS(tblTargetVsActual[Target Amount],tblTargetVsActual[MonthYear],M18) -> 28938000 | O18: =SUMIFS(tblTargetVsActual[Actual Sales],tblTargetVsActual[MonthYear],M18) -> 4931500 | P18: =O18-N18 -> -24006500 | Q18: =IFERROR(O18/N18,0) -> 0.17041606 | S18: =SUMIFS(tblSalesTargets[Target Amount],tblSalesTargets[MonthYear],A18,tblSalesTargets[Salesperson ID],C18) -> 2266000 | T18: =SUMIFS(tblSalesTransactions[Sales Amount],tblSalesTransactions[Salesperson ID],C18,tblSalesTransactions[Date],">="&A18,tblSalesTransactions[Date],"<"&EDATE(A18,1)) -> 287250 | U18: =F18 -> 2266000 | V18: =G18 -> 287250 | W18: =S18=U18 -> TRUE | X18: =T18=V18 -> TRUE
A19: 46054 | B19: 2 | C19: SP004 | D19: R002 | E19: C002 | F19: =SUMIFS(tblSalesTargets[Target Amount],tblSalesTargets[MonthYear],A19,tblSalesTargets[Salesperson ID],C19) -> 2781000 | G19: =SUMIFS(tblSalesTransactions[Sales Amount],tblSalesTransactions[Salesperson ID],C19,tblSalesTransactions[Date],">="&A19,tblSalesTransactions[Date],"<"&EDATE(A19,1)) -> 505500 | H19: =G19-F19 -> -2275500 | I19: =IFERROR(G19/F19,0) -> 0.18176915 | J19: =IF(I19>=1,"Achieved",IF(I19>=0.9,"Near Target","Below Target")) -> Below Target | M19: =EDATE(M18,1) -> 46266 | N19: =SUMIFS(tblTargetVsActual[Target Amount],tblTargetVsActual[MonthYear],M19) -> 29211000 | O19: =SUMIFS(tblTargetVsActual[Actual Sales],tblTargetVsActual[MonthYear],M19) -> 5190750 | P19: =O19-N19 -> -24020250 | Q19: =IFERROR(O19/N19,0) -> 0.17769847 | S19: =SUMIFS(tblSalesTargets[Target Amount],tblSalesTargets[MonthYear],A19,tblSalesTargets[Salesperson ID],C19) -> 2781000 | T19: =SUMIFS(tblSalesTransactions[Sales Amount],tblSalesTransactions[Salesperson ID],C19,tblSalesTransactions[Date],">="&A19,tblSalesTransactions[Date],"<"&EDATE(A19,1)) -> 505500 | U19: =F19 -> 2781000 | V19: =G19 -> 505500 | W19: =S19=U19 -> TRUE | X19: =T19=V19 -> TRUE
A20: 46054 | B20: 2 | C20: SP005 | D20: R002 | E20: C002 | F20: =SUMIFS(tblSalesTargets[Target Amount],tblSalesTargets[MonthYear],A20,tblSalesTargets[Salesperson ID],C20) -> 2575000 | G20: =SUMIFS(tblSalesTransactions[Sales Amount],tblSalesTransactions[Salesperson ID],C20,tblSalesTransactions[Date],">="&A20,tblSalesTransactions[Date],"<"&EDATE(A20,1)) -> 504000 | H20: =G20-F20 -> -2071000 | I20: =IFERROR(G20/F20,0) -> 0.19572816 | J20: =IF(I20>=1,"Achieved",IF(I20>=0.9,"Near Target","Below Target")) -> Below Target | M20: =EDATE(M19,1) -> 46296 | N20: =SUMIFS(tblTargetVsActual[Target Amount],tblTargetVsActual[MonthYear],M20) -> 30030000 | O20: =SUMIFS(tblTargetVsActual[Actual Sales],tblTargetVsActual[MonthYear],M20) -> 5458250 | P20: =O20-N20 -> -24571750 | Q20: =IFERROR(O20/N20,0) -> 0.18175991 | S20: =SUMIFS(tblSalesTargets[Target Amount],tblSalesTargets[MonthYear],A20,tblSalesTargets[Salesperson ID],C20) -> 2575000 | T20: =SUMIFS(tblSalesTransactions[Sales Amount],tblSalesTransactions[Salesperson ID],C20,tblSalesTransactions[Date],">="&A20,tblSalesTransactions[Date],"<"&EDATE(A20,1)) -> 504000 | U20: =F20 -> 2575000 | V20: =G20 -> 504000 | W20: =S20=U20 -> TRUE | X20: =T20=V20 -> TRUE
A21: 46054 | B21: 2 | C21: SP006 | D21: R002 | E21: C002 | F21: =SUMIFS(tblSalesTargets[Target Amount],tblSalesTargets[MonthYear],A21,tblSalesTargets[Salesperson ID],C21) -> 2369000 | G21: =SUMIFS(tblSalesTransactions[Sales Amount],tblSalesTransactions[Salesperson ID],C21,tblSalesTransactions[Date],">="&A21,tblSalesTransactions[Date],"<"&EDATE(A21,1)) -> 329000 | H21: =G21-F21 -> -2040000 | I21: =IFERROR(G21/F21,0) -> 0.13887716 | J21: =IF(I21>=1,"Achieved",IF(I21>=0.9,"Near Target","Below Target")) -> Below Target | M21: =EDATE(M20,1) -> 46327 | N21: =SUMIFS(tblTargetVsActual[Target Amount],tblTargetVsActual[MonthYear],M21) -> 30576000 | O21: =SUMIFS(tblTargetVsActual[Actual Sales],tblTargetVsActual[MonthYear],M21) -> 5931000 | P21: =O21-N21 -> -24645000 | Q21: =IFERROR(O21/N21,0) -> 0.19397567 | S21: =SUMIFS(tblSalesTargets[Target Amount],tblSalesTargets[MonthYear],A21,tblSalesTargets[Salesperson ID],C21) -> 2369000 | T21: =SUMIFS(tblSalesTransactions[Sales Amount],tblSalesTransactions[Salesperson ID],C21,tblSalesTransactions[Date],">="&A21,tblSalesTransactions[Date],"<"&EDATE(A21,1)) -> 329000 | U21: =F21 -> 2369000 | V21: =G21 -> 329000 | W21: =S21=U21 -> TRUE | X21: =T21=V21 -> TRUE
A22: 46054 | B22: 2 | C22: SP007 | D22: R003 | E22: C003 | F22: =SUMIFS(tblSalesTargets[Target Amount],tblSalesTargets[MonthYear],A22,tblSalesTargets[Salesperson ID],C22) -> 2472000 | G22: =SUMIFS(tblSalesTransactions[Sales Amount],tblSalesTransactions[Salesperson ID],C22,tblSalesTransactions[Date],">="&A22,tblSalesTransactions[Date],"<"&EDATE(A22,1)) -> 486000 | H22: =G22-F22 -> -1986000 | I22: =IFERROR(G22/F22,0) -> 0.19660194 | J22: =IF(I22>=1,"Achieved",IF(I22>=0.9,"Near Target","Below Target")) -> Below Target | M22: =EDATE(M21,1) -> 46357 | N22: =SUMIFS(tblTargetVsActual[Target Amount],tblTargetVsActual[MonthYear],M22) -> 32760000 | O22: =SUMIFS(tblTargetVsActual[Actual Sales],tblTargetVsActual[MonthYear],M22) -> 6607500 | P22: =O22-N22 -> -26152500 | Q22: =IFERROR(O22/N22,0) -> 0.20169414 | S22: =SUMIFS(tblSalesTargets[Target Amount],tblSalesTargets[MonthYear],A22,tblSalesTargets[Salesperson ID],C22) -> 2472000 | T22: =SUMIFS(tblSalesTransactions[Sales Amount],tblSalesTransactions[Salesperson ID],C22,tblSalesTransactions[Date],">="&A22,tblSalesTransactions[Date],"<"&EDATE(A22,1)) -> 486000 | U22: =F22 -> 2472000 | V22: =G22 -> 486000 | W22: =S22=U22 -> TRUE | X22: =T22=V22 -> TRUE
A23: 46054 | B23: 2 | C23: SP008 | D23: R003 | E23: C003 | F23: =SUMIFS(tblSalesTargets[Target Amount],tblSalesTargets[MonthYear],A23,tblSalesTargets[Salesperson ID],C23) -> 2266000 | G23: =SUMIFS(tblSalesTransactions[Sales Amount],tblSalesTransactions[Salesperson ID],C23,tblSalesTransactions[Date],">="&A23,tblSalesTransactions[Date],"<"&EDATE(A23,1)) -> 496500 | H23: =G23-F23 -> -1769500 | I23: =IFERROR(G23/F23,0) -> 0.21910856 | J23: =IF(I23>=1,"Achieved",IF(I23>=0.9,"Near Target","Below Target")) -> Below Target | S23: =SUMIFS(tblSalesTargets[Target Amount],tblSalesTargets[MonthYear],A23,tblSalesTargets[Salesperson ID],C23) -> 2266000 | T23: =SUMIFS(tblSalesTransactions[Sales Amount],tblSalesTransactions[Salesperson ID],C23,tblSalesTransactions[Date],">="&A23,tblSalesTransactions[Date],"<"&EDATE(A23,1)) -> 496500 | U23: =F23 -> 2266000 | V23: =G23 -> 496500 | W23: =S23=U23 -> TRUE | X23: =T23=V23 -> TRUE
A24: 46054 | B24: 2 | C24: SP009 | D24: R003 | E24: C003 | F24: =SUMIFS(tblSalesTargets[Target Amount],tblSalesTargets[MonthYear],A24,tblSalesTargets[Salesperson ID],C24) -> 2163000 | G24: =SUMIFS(tblSalesTransactions[Sales Amount],tblSalesTransactions[Salesperson ID],C24,tblSalesTransactions[Date],">="&A24,tblSalesTransactions[Date],"<"&EDATE(A24,1)) -> 302500 | H24: =G24-F24 -> -1860500 | I24: =IFERROR(G24/F24,0) -> 0.13985206 | J24: =IF(I24>=1,"Achieved",IF(I24>=0.9,"Near Target","Below Target")) -> Below Target | S24: =SUMIFS(tblSalesTargets[Target Amount],tblSalesTargets[MonthYear],A24,tblSalesTargets[Salesperson ID],C24) -> 2163000 | T24: =SUMIFS(tblSalesTransactions[Sales Amount],tblSalesTransactions[Salesperson ID],C24,tblSalesTransactions[Date],">="&A24,tblSalesTransactions[Date],"<"&EDATE(A24,1)) -> 302500 | U24: =F24 -> 2163000 | V24: =G24 -> 302500 | W24: =S24=U24 -> TRUE | X24: =T24=V24 -> TRUE
A25: 46054 | B25: 2 | C25: SP010 | D25: R004 | E25: C004 | F25: =SUMIFS(tblSalesTargets[Target Amount],tblSalesTargets[MonthYear],A25,tblSalesTargets[Salesperson ID],C25) -> 2266000 | G25: =SUMIFS(tblSalesTransactions[Sales Amount],tblSalesTransactions[Salesperson ID],C25,tblSalesTransactions[Date],">="&A25,tblSalesTransactions[Date],"<"&EDATE(A25,1)) -> 272500 | H25: =G25-F25 -> -1993500 | I25: =IFERROR(G25/F25,0) -> 0.12025596 | J25: =IF(I25>=1,"Achieved",IF(I25>=0.9,"Near Target","Below Target")) -> Below Target | S25: =SUMIFS(tblSalesTargets[Target Amount],tblSalesTargets[MonthYear],A25,tblSalesTargets[Salesperson ID],C25) -> 2266000 | T25: =SUMIFS(tblSalesTransactions[Sales Amount],tblSalesTransactions[Salesperson ID],C25,tblSalesTransactions[Date],">="&A25,tblSalesTransactions[Date],"<"&EDATE(A25,1)) -> 272500 | U25: =F25 -> 2266000 | V25: =G25 -> 272500 | W25: =S25=U25 -> TRUE | X25: =T25=V25 -> TRUE
A26: 46054 | B26: 2 | C26: SP011 | D26: R004 | E26: C004 | F26: =SUMIFS(tblSalesTargets[Target Amount],tblSalesTargets[MonthYear],A26,tblSalesTargets[Salesperson ID],C26) -> 2060000 | G26: =SUMIFS(tblSalesTransactions[Sales Amount],tblSalesTransactions[Salesperson ID],C26,tblSalesTransactions[Date],">="&A26,tblSalesTransactions[Date],"<"&EDATE(A26,1)) -> 294500 | H26: =G26-F26 -> -1765500 | I26: =IFERROR(G26/F26,0) -> 0.14296117 | J26: =IF(I26>=1,"Achieved",IF(I26>=0.9,"Near Target","Below Target")) -> Below Target | S26: =SUMIFS(tblSalesTargets[Target Amount],tblSalesTargets[MonthYear],A26,tblSalesTargets[Salesperson ID],C26) -> 2060000 | T26: =SUMIFS(tblSalesTransactions[Sales Amount],tblSalesTransactions[Salesperson ID],C26,tblSalesTransactions[Date],">="&A26,tblSalesTransactions[Date],"<"&EDATE(A26,1)) -> 294500 | U26: =F26 -> 2060000 | V26: =G26 -> 294500 | W26: =S26=U26 -> TRUE | X26: =T26=V26 -> TRUE
A27: 46054 | B27: 2 | C27: SP012 | D27: R004 | E27: C004 | F27: =SUMIFS(tblSalesTargets[Target Amount],tblSalesTargets[MonthYear],A27,tblSalesTargets[Salesperson ID],C27) -> 1957000 | G27: =SUMIFS(tblSalesTransactions[Sales Amount],tblSalesTransactions[Salesperson ID],C27,tblSalesTransactions[Date],">="&A27,tblSalesTransactions[Date],"<"&EDATE(A27,1)) -> 256000 | H27: =G27-F27 -> -1701000 | I27: =IFERROR(G27/F27,0) -> 0.13081247 | J27: =IF(I27>=1,"Achieved",IF(I27>=0.9,"Near Target","Below Target")) -> Below Target | S27: =SUMIFS(tblSalesTargets[Target Amount],tblSalesTargets[MonthYear],A27,tblSalesTargets[Salesperson ID],C27) -> 1957000 | T27: =SUMIFS(tblSalesTransactions[Sales Amount],tblSalesTransactions[Salesperson ID],C27,tblSalesTransactions[Date],">="&A27,tblSalesTransactions[Date],"<"&EDATE(A27,1)) -> 256000 | U27: =F27 -> 1957000 | V27: =G27 -> 256000 | W27: =S27=U27 -> TRUE | X27: =T27=V27 -> TRUE
A28: 46082 | B28: 3 | C28: SP001 | D28: R001 | E28: C001 | F28: =SUMIFS(tblSalesTargets[Target Amount],tblSalesTargets[MonthYear],A28,tblSalesTargets[Salesperson ID],C28) -> 2625000 | G28: =SUMIFS(tblSalesTransactions[Sales Amount],tblSalesTransactions[Salesperson ID],C28,tblSalesTransactions[Date],">="&A28,tblSalesTransactions[Date],"<"&EDATE(A28,1)) -> 238250 | H28: =G28-F28 -> -2386750 | I28: =IFERROR(G28/F28,0) -> 0.090761905 | J28: =IF(I28>=1,"Achieved",IF(I28>=0.9,"Near Target","Below Target")) -> Below Target | S28: =SUMIFS(tblSalesTargets[Target Amount],tblSalesTargets[MonthYear],A28,tblSalesTargets[Salesperson ID],C28) -> 2625000 | T28: =SUMIFS(tblSalesTransactions[Sales Amount],tblSalesTransactions[Salesperson ID],C28,tblSalesTransactions[Date],">="&A28,tblSalesTransactions[Date],"<"&EDATE(A28,1)) -> 238250 | U28: =F28 -> 2625000 | V28: =G28 -> 238250 | W28: =S28=U28 -> TRUE | X28: =T28=V28 -> TRUE
A29: 46082 | B29: 3 | C29: SP002 | D29: R001 | E29: C001 | F29: =SUMIFS(tblSalesTargets[Target Amount],tblSalesTargets[MonthYear],A29,tblSalesTargets[Salesperson ID],C29) -> 2415000 | G29: =SUMIFS(tblSalesTransactions[Sales Amount],tblSalesTransactions[Salesperson ID],C29,tblSalesTransactions[Date],">="&A29,tblSalesTransactions[Date],"<"&EDATE(A29,1)) -> 348000 | H29: =G29-F29 -> -2067000 | I29: =IFERROR(G29/F29,0) -> 0.14409938 | J29: =IF(I29>=1,"Achieved",IF(I29>=0.9,"Near Target","Below Target")) -> Below Target | S29: =SUMIFS(tblSalesTargets[Target Amount],tblSalesTargets[MonthYear],A29,tblSalesTargets[Salesperson ID],C29) -> 2415000 | T29: =SUMIFS(tblSalesTransactions[Sales Amount],tblSalesTransactions[Salesperson ID],C29,tblSalesTransactions[Date],">="&A29,tblSalesTransactions[Date],"<"&EDATE(A29,1)) -> 348000 | U29: =F29 -> 2415000 | V29: =G29 -> 348000 | W29: =S29=U29 -> TRUE | X29: =T29=V29 -> TRUE
A30: 46082 | B30: 3 | C30: SP003 | D30: R001 | E30: C001 | F30: =SUMIFS(tblSalesTargets[Target Amount],tblSalesTargets[MonthYear],A30,tblSalesTargets[Salesperson ID],C30) -> 2310000 | G30: =SUMIFS(tblSalesTransactions[Sales Amount],tblSalesTransactions[Salesperson ID],C30,tblSalesTransactions[Date],">="&A30,tblSalesTransactions[Date],"<"&EDATE(A30,1)) -> 316000 | H30: =G30-F30 -> -1994000 | I30: =IFERROR(G30/F30,0) -> 0.13679654 | J30: =IF(I30>=1,"Achieved",IF(I30>=0.9,"Near Target","Below Target")) -> Below Target | S30: =SUMIFS(tblSalesTargets[Target Amount],tblSalesTargets[MonthYear],A30,tblSalesTargets[Salesperson ID],C30) -> 2310000 | T30: =SUMIFS(tblSalesTransactions[Sales Amount],tblSalesTransactions[Salesperson ID],C30,tblSalesTransactions[Date],">="&A30,tblSalesTransactions[Date],"<"&EDATE(A30,1)) -> 316000 | U30: =F30 -> 2310000 | V30: =G30 -> 316000 | W30: =S30=U30 -> TRUE | X30: =T30=V30 -> TRUE
A31: 46082 | B31: 3 | C31: SP004 | D31: R002 | E31: C002 | F31: =SUMIFS(tblSalesTargets[Target Amount],tblSalesTargets[MonthYear],A31,tblSalesTargets[Salesperson ID],C31) -> 2835000 | G31: =SUMIFS(tblSalesTransactions[Sales Amount],tblSalesTransactions[Salesperson ID],C31,tblSalesTransactions[Date],">="&A31,tblSalesTransactions[Date],"<"&EDATE(A31,1)) -> 462500 | H31: =G31-F31 -> -2372500 | I31: =IFERROR(G31/F31,0) -> 0.16313933 | J31: =IF(I31>=1,"Achieved",IF(I31>=0.9,"Near Target","Below Target")) -> Below Target | S31: =SUMIFS(tblSalesTargets[Target Amount],tblSalesTargets[MonthYear],A31,tblSalesTargets[Salesperson ID],C31) -> 2835000 | T31: =SUMIFS(tblSalesTransactions[Sales Amount],tblSalesTransactions[Salesperson ID],C31,tblSalesTransactions[Date],">="&A31,tblSalesTransactions[Date],"<"&EDATE(A31,1)) -> 462500 | U31: =F31 -> 2835000 | V31: =G31 -> 462500 | W31: =S31=U31 -> TRUE | X31: =T31=V31 -> TRUE
A32: 46082 | B32: 3 | C32: SP005 | D32: R002 | E32: C002 | F32: =SUMIFS(tblSalesTargets[Target Amount],tblSalesTargets[MonthYear],A32,tblSalesTargets[Salesperson ID],C32) -> 2625000 | G32: =SUMIFS(tblSalesTransactions[Sales Amount],tblSalesTransactions[Salesperson ID],C32,tblSalesTransactions[Date],">="&A32,tblSalesTransactions[Date],"<"&EDATE(A32,1)) -> 408000 | H32: =G32-F32 -> -2217000 | I32: =IFERROR(G32/F32,0) -> 0.15542857 | J32: =IF(I32>=1,"Achieved",IF(I32>=0.9,"Near Target","Below Target")) -> Below Target | S32: =SUMIFS(tblSalesTargets[Target Amount],tblSalesTargets[MonthYear],A32,tblSalesTargets[Salesperson ID],C32) -> 2625000 | T32: =SUMIFS(tblSalesTransactions[Sales Amount],tblSalesTransactions[Salesperson ID],C32,tblSalesTransactions[Date],">="&A32,tblSalesTransactions[Date],"<"&EDATE(A32,1)) -> 408000 | U32: =F32 -> 2625000 | V32: =G32 -> 408000 | W32: =S32=U32 -> TRUE | X32: =T32=V32 -> TRUE
A33: 46082 | B33: 3 | C33: SP006 | D33: R002 | E33: C002 | F33: =SUMIFS(tblSalesTargets[Target Amount],tblSalesTargets[MonthYear],A33,tblSalesTargets[Salesperson ID],C33) -> 2415000 | G33: =SUMIFS(tblSalesTransactions[Sales Amount],tblSalesTransactions[Salesperson ID],C33,tblSalesTransactions[Date],">="&A33,tblSalesTransactions[Date],"<"&EDATE(A33,1)) -> 455500 | H33: =G33-F33 -> -1959500 | I33: =IFERROR(G33/F33,0) -> 0.18861284 | J33: =IF(I33>=1,"Achieved",IF(I33>=0.9,"Near Target","Below Target")) -> Below Target | S33: =SUMIFS(tblSalesTargets[Target Amount],tblSalesTargets[MonthYear],A33,tblSalesTargets[Salesperson ID],C33) -> 2415000 | T33: =SUMIFS(tblSalesTransactions[Sales Amount],tblSalesTransactions[Salesperson ID],C33,tblSalesTransactions[Date],">="&A33,tblSalesTransactions[Date],"<"&EDATE(A33,1)) -> 455500 | U33: =F33 -> 2415000 | V33: =G33 -> 455500 | W33: =S33=U33 -> TRUE | X33: =T33=V33 -> TRUE
A34: 46082 | B34: 3 | C34: SP007 | D34: R003 | E34: C003 | F34: =SUMIFS(tblSalesTargets[Target Amount],tblSalesTargets[MonthYear],A34,tblSalesTargets[Salesperson ID],C34) -> 2520000 | G34: =SUMIFS(tblSalesTransactions[Sales Amount],tblSalesTransactions[Salesperson ID],C34,tblSalesTransactions[Date],">="&A34,tblSalesTransactions[Date],"<"&EDATE(A34,1)) -> 496500 | H34: =G34-F34 -> -2023500 | I34: =IFERROR(G34/F34,0) -> 0.19702381 | J34: =IF(I34>=1,"Achieved",IF(I34>=0.9,"Near Target","Below Target")) -> Below Target | S34: =SUMIFS(tblSalesTargets[Target Amount],tblSalesTargets[MonthYear],A34,tblSalesTargets[Salesperson ID],C34) -> 2520000 | T34: =SUMIFS(tblSalesTransactions[Sales Amount],tblSalesTransactions[Salesperson ID],C34,tblSalesTransactions[Date],">="&A34,tblSalesTransactions[Date],"<"&EDATE(A34,1)) -> 496500 | U34: =F34 -> 2520000 | V34: =G34 -> 496500 | W34: =S34=U34 -> TRUE | X34: =T34=V34 -> TRUE
... A147: 46357 | B147: 12 | C147: SP012 | D147: R004 | E147: C004 | F147: =SUMIFS(tblSalesTargets[Target Amount],tblSalesTargets[MonthYear],A147,tblSalesTargets[Salesperson ID],C147) -> 2280000 | G147: =SUMIFS(tblSalesTransactions[Sales Amount],tblSalesTransactions[Salesperson ID],C147,tblSalesTransactions[Date],">="&A147,tblSalesTransactions[Date],"<"&EDATE(A147,1)) -> 415250 | H147: =G147-F147 -> -1864750 | I147: =IFERROR(G147/F147,0) -> 0.18212719 | J147: =IF(I147>=1,"Achieved",IF(I147>=0.9,"Near Target","Below Target")) -> Below Target | S147: =SUMIFS(tblSalesTargets[Target Amount],tblSalesTargets[MonthYear],A147,tblSalesTargets[Salesperson ID],C147) -> 2280000 | T147: =SUMIFS(tblSalesTransactions[Sales Amount],tblSalesTransactions[Salesperson ID],C147,tblSalesTransactions[Date],">="&A147,tblSalesTransactions[Date],"<"&EDATE(A147,1)) -> 415250 | U147: =F147 -> 2280000 | V147: =G147 -> 415250 | W147: =S147=U147 -> TRUE | X147: =T147=V147 -> TRUE
F148: =SUBTOTAL(109,tblTargetVsActual[Target Amount]) -> 348075000 | G148: =SUBTOTAL(109,tblTargetVsActual[Actual Sales]) -> 60255750 | H148: =SUBTOTAL(109,tblTargetVsActual[SALES VARIANCE]) -> -287819250 | I148: =tblTargetVsActual[[#Totals],[Actual Sales]]/tblTargetVsActual[[#Totals],[Target Amount]] -> 0.1731114

Sheet 14_Distributor_Analysis
A1: Distributor Analysis
A3: Distributor ID | B3: Distributor Name | C3: City ID | D3: Salesperson ID | E3: Total Sales | F3: Transaction Count | G3: Average Transaction Value | H3: Closing Stock Qty | I3: Stock Value | J3: Outstanding Amount | K3: Collection Status | L3: Stock Status | M3: Potential Slow-Moving Indicator | O3: Distributor KPI Summary
A4: D001 | B4: =IFERROR(INDEX(tblDistributors[Distributor Name],MATCH(A4,tblDistributors[Distributor ID],0)),"") -> Karachi Distributors | C4: =IFERROR(INDEX(tblDistributors[City ID],MATCH(A4,tblDistributors[Distributor ID],0)),"") -> C001 | D4: =IFERROR(INDEX(tblDistributors[Salesperson ID],MATCH(A4,tblDistributors[Distributor ID],0)),"") -> SP001 | E4: =SUMIFS(tblSalesTransactions[Sales Amount],tblSalesTransactions[Distributor ID],A4) -> 3296500 | F4: =COUNTIFS(tblSalesTransactions[Distributor ID],A4) -> 25 | G4: =IFERROR(E4/F4,0) -> 131860 | H4: =SUMIFS(tblInventory[Closing Stock Qty],tblInventory[Distributor ID],A4,tblInventory[Snapshot Date],'02_Control_Panel'!$B$5) -> 248 | I4: =SUMIFS(tblInventory[Stock Value],tblInventory[Distributor ID],A4,tblInventory[Snapshot Date],'02_Control_Panel'!$B$5) -> 324900 | J4: =SUMIFS(tblCollections[Outstanding Amount],tblCollections[Distributor ID],A4) -> 0 | K4: =IF(J4=0,"Paid",IF(J4>0,"Outstanding","Review")) -> Paid | L4: =IF(COUNTIFS(tblInventory[Distributor ID],A4,tblInventory[Snapshot Date],'02_Control_Panel'!$B$5,tblInventory[Stock Status],"High Stock")>0,"High Stock","Normal") -> High Stock | M4: =IF(AND(L4="High Stock",E4>0),"Potential Slow-Moving","Normal") -> Potential Slow-Moving | O4: Total Distributors | P4: =COUNTA(tblDistributorAnalysis[Distributor ID]) -> 12
A5: D002 | B5: =IFERROR(INDEX(tblDistributors[Distributor Name],MATCH(A5,tblDistributors[Distributor ID],0)),"") -> Metro Wholesale Karachi | C5: =IFERROR(INDEX(tblDistributors[City ID],MATCH(A5,tblDistributors[Distributor ID],0)),"") -> C001 | D5: =IFERROR(INDEX(tblDistributors[Salesperson ID],MATCH(A5,tblDistributors[Distributor ID],0)),"") -> SP002 | E5: =SUMIFS(tblSalesTransactions[Sales Amount],tblSalesTransactions[Distributor ID],A5) -> 4262000 | F5: =COUNTIFS(tblSalesTransactions[Distributor ID],A5) -> 25 | G5: =IFERROR(E5/F5,0) -> 170480 | H5: =SUMIFS(tblInventory[Closing Stock Qty],tblInventory[Distributor ID],A5,tblInventory[Snapshot Date],'02_Control_Panel'!$B$5) -> 221 | I5: =SUMIFS(tblInventory[Stock Value],tblInventory[Distributor ID],A5,tblInventory[Snapshot Date],'02_Control_Panel'!$B$5) -> 393000 | J5: =SUMIFS(tblCollections[Outstanding Amount],tblCollections[Distributor ID],A5) -> 0 | K5: =IF(J5=0,"Paid",IF(J5>0,"Outstanding","Review")) -> Paid | L5: =IF(COUNTIFS(tblInventory[Distributor ID],A5,tblInventory[Snapshot Date],'02_Control_Panel'!$B$5,tblInventory[Stock Status],"High Stock")>0,"High Stock","Normal") -> High Stock | M5: =IF(AND(L5="High Stock",E5>0),"Potential Slow-Moving","Normal") -> Potential Slow-Moving | O5: Total Sales | P5: =SUM(tblDistributorAnalysis[Total Sales]) -> 60255750
A6: D003 | B6: =IFERROR(INDEX(tblDistributors[Distributor Name],MATCH(A6,tblDistributors[Distributor ID],0)),"") -> Sindh Trade Network | C6: =IFERROR(INDEX(tblDistributors[City ID],MATCH(A6,tblDistributors[Distributor ID],0)),"") -> C001 | D6: =IFERROR(INDEX(tblDistributors[Salesperson ID],MATCH(A6,tblDistributors[Distributor ID],0)),"") -> SP003 | E6: =SUMIFS(tblSalesTransactions[Sales Amount],tblSalesTransactions[Distributor ID],A6) -> 3863500 | F6: =COUNTIFS(tblSalesTransactions[Distributor ID],A6) -> 25 | G6: =IFERROR(E6/F6,0) -> 154540 | H6: =SUMIFS(tblInventory[Closing Stock Qty],tblInventory[Distributor ID],A6,tblInventory[Snapshot Date],'02_Control_Panel'!$B$5) -> 146 | I6: =SUMIFS(tblInventory[Stock Value],tblInventory[Distributor ID],A6,tblInventory[Snapshot Date],'02_Control_Panel'!$B$5) -> 227850 | J6: =SUMIFS(tblCollections[Outstanding Amount],tblCollections[Distributor ID],A6) -> 492000 | K6: =IF(J6=0,"Paid",IF(J6>0,"Outstanding","Review")) -> Outstanding | L6: =IF(COUNTIFS(tblInventory[Distributor ID],A6,tblInventory[Snapshot Date],'02_Control_Panel'!$B$5,tblInventory[Stock Status],"High Stock")>0,"High Stock","Normal") -> Normal | M6: =IF(AND(L6="High Stock",E6>0),"Potential Slow-Moving","Normal") -> Normal | O6: Total Stock Value | P6: =SUM(tblDistributorAnalysis[Stock Value]) -> 3553500
A7: D004 | B7: =IFERROR(INDEX(tblDistributors[Distributor Name],MATCH(A7,tblDistributors[Distributor ID],0)),"") -> Lahore Trading Co. | C7: =IFERROR(INDEX(tblDistributors[City ID],MATCH(A7,tblDistributors[Distributor ID],0)),"") -> C002 | D7: =IFERROR(INDEX(tblDistributors[Salesperson ID],MATCH(A7,tblDistributors[Distributor ID],0)),"") -> SP004 | E7: =SUMIFS(tblSalesTransactions[Sales Amount],tblSalesTransactions[Distributor ID],A7) -> 6362250 | F7: =COUNTIFS(tblSalesTransactions[Distributor ID],A7) -> 25 | G7: =IFERROR(E7/F7,0) -> 254490 | H7: =SUMIFS(tblInventory[Closing Stock Qty],tblInventory[Distributor ID],A7,tblInventory[Snapshot Date],'02_Control_Panel'!$B$5) -> 244 | I7: =SUMIFS(tblInventory[Stock Value],tblInventory[Distributor ID],A7,tblInventory[Snapshot Date],'02_Control_Panel'!$B$5) -> 325100 | J7: =SUMIFS(tblCollections[Outstanding Amount],tblCollections[Distributor ID],A7) -> 163000 | K7: =IF(J7=0,"Paid",IF(J7>0,"Outstanding","Review")) -> Outstanding | L7: =IF(COUNTIFS(tblInventory[Distributor ID],A7,tblInventory[Snapshot Date],'02_Control_Panel'!$B$5,tblInventory[Stock Status],"High Stock")>0,"High Stock","Normal") -> High Stock | M7: =IF(AND(L7="High Stock",E7>0),"Potential Slow-Moving","Normal") -> Potential Slow-Moving | O7: Total Outstanding | P7: =SUM(tblDistributorAnalysis[Outstanding Amount]) -> 2654000
A8: D005 | B8: =IFERROR(INDEX(tblDistributors[Distributor Name],MATCH(A8,tblDistributors[Distributor ID],0)),"") -> Punjab Distribution House | C8: =IFERROR(INDEX(tblDistributors[City ID],MATCH(A8,tblDistributors[Distributor ID],0)),"") -> C002 | D8: =IFERROR(INDEX(tblDistributors[Salesperson ID],MATCH(A8,tblDistributors[Distributor ID],0)),"") -> SP005 | E8: =SUMIFS(tblSalesTransactions[Sales Amount],tblSalesTransactions[Distributor ID],A8) -> 6537500 | F8: =COUNTIFS(tblSalesTransactions[Distributor ID],A8) -> 25 | G8: =IFERROR(E8/F8,0) -> 261500 | H8: =SUMIFS(tblInventory[Closing Stock Qty],tblInventory[Distributor ID],A8,tblInventory[Snapshot Date],'02_Control_Panel'!$B$5) -> 218 | I8: =SUMIFS(tblInventory[Stock Value],tblInventory[Distributor ID],A8,tblInventory[Snapshot Date],'02_Control_Panel'!$B$5) -> 397800 | J8: =SUMIFS(tblCollections[Outstanding Amount],tblCollections[Distributor ID],A8) -> 0 | K8: =IF(J8=0,"Paid",IF(J8>0,"Outstanding","Review")) -> Paid | L8: =IF(COUNTIFS(tblInventory[Distributor ID],A8,tblInventory[Snapshot Date],'02_Control_Panel'!$B$5,tblInventory[Stock Status],"High Stock")>0,"High Stock","Normal") -> High Stock | M8: =IF(AND(L8="High Stock",E8>0),"Potential Slow-Moving","Normal") -> Potential Slow-Moving | O8: High Stock Distributors | P8: =COUNTIF(tblDistributorAnalysis[Stock Status],"High Stock") -> 5
A9: D006 | B9: =IFERROR(INDEX(tblDistributors[Distributor Name],MATCH(A9,tblDistributors[Distributor ID],0)),"") -> Lahore Wholesale Mart | C9: =IFERROR(INDEX(tblDistributors[City ID],MATCH(A9,tblDistributors[Distributor ID],0)),"") -> C002 | D9: =IFERROR(INDEX(tblDistributors[Salesperson ID],MATCH(A9,tblDistributors[Distributor ID],0)),"") -> SP006 | E9: =SUMIFS(tblSalesTransactions[Sales Amount],tblSalesTransactions[Distributor ID],A9) -> 5038250 | F9: =COUNTIFS(tblSalesTransactions[Distributor ID],A9) -> 25 | G9: =IFERROR(E9/F9,0) -> 201530 | H9: =SUMIFS(tblInventory[Closing Stock Qty],tblInventory[Distributor ID],A9,tblInventory[Snapshot Date],'02_Control_Panel'!$B$5) -> 136 | I9: =SUMIFS(tblInventory[Stock Value],tblInventory[Distributor ID],A9,tblInventory[Snapshot Date],'02_Control_Panel'!$B$5) -> 229000 | J9: =SUMIFS(tblCollections[Outstanding Amount],tblCollections[Distributor ID],A9) -> 88000 | K9: =IF(J9=0,"Paid",IF(J9>0,"Outstanding","Review")) -> Outstanding | L9: =IF(COUNTIFS(tblInventory[Distributor ID],A9,tblInventory[Snapshot Date],'02_Control_Panel'!$B$5,tblInventory[Stock Status],"High Stock")>0,"High Stock","Normal") -> Normal | M9: =IF(AND(L9="High Stock",E9>0),"Potential Slow-Moving","Normal") -> Normal | O9: Potential Slow-Moving | P9: =COUNTIF(tblDistributorAnalysis[Potential Slow-Moving Indicator],"Potential Slow-Moving") -> 5
A10: D007 | B10: =IFERROR(INDEX(tblDistributors[Distributor Name],MATCH(A10,tblDistributors[Distributor ID],0)),"") -> Capital Distribution Co. | C10: =IFERROR(INDEX(tblDistributors[City ID],MATCH(A10,tblDistributors[Distributor ID],0)),"") -> C003 | D10: =IFERROR(INDEX(tblDistributors[Salesperson ID],MATCH(A10,tblDistributors[Distributor ID],0)),"") -> SP007 | E10: =SUMIFS(tblSalesTransactions[Sales Amount],tblSalesTransactions[Distributor ID],A10) -> 7064000 | F10: =COUNTIFS(tblSalesTransactions[Distributor ID],A10) -> 25 | G10: =IFERROR(E10/F10,0) -> 282560 | H10: =SUMIFS(tblInventory[Closing Stock Qty],tblInventory[Distributor ID],A10,tblInventory[Snapshot Date],'02_Control_Panel'!$B$5) -> 148 | I10: =SUMIFS(tblInventory[Stock Value],tblInventory[Distributor ID],A10,tblInventory[Snapshot Date],'02_Control_Panel'!$B$5) -> 254300 | J10: =SUMIFS(tblCollections[Outstanding Amount],tblCollections[Distributor ID],A10) -> 132000 | K10: =IF(J10=0,"Paid",IF(J10>0,"Outstanding","Review")) -> Outstanding | L10: =IF(COUNTIFS(tblInventory[Distributor ID],A10,tblInventory[Snapshot Date],'02_Control_Panel'!$B$5,tblInventory[Stock Status],"High Stock")>0,"High Stock","Normal") -> Normal | M10: =IF(AND(L10="High Stock",E10>0),"Potential Slow-Moving","Normal") -> Normal
A11: D008 | B11: =IFERROR(INDEX(tblDistributors[Distributor Name],MATCH(A11,tblDistributors[Distributor ID],0)),"") -> Islamabad Trade Link | C11: =IFERROR(INDEX(tblDistributors[City ID],MATCH(A11,tblDistributors[Distributor ID],0)),"") -> C003 | D11: =IFERROR(INDEX(tblDistributors[Salesperson ID],MATCH(A11,tblDistributors[Distributor ID],0)),"") -> SP008 | E11: =SUMIFS(tblSalesTransactions[Sales Amount],tblSalesTransactions[Distributor ID],A11) -> 7393000 | F11: =COUNTIFS(tblSalesTransactions[Distributor ID],A11) -> 25 | G11: =IFERROR(E11/F11,0) -> 295720 | H11: =SUMIFS(tblInventory[Closing Stock Qty],tblInventory[Distributor ID],A11,tblInventory[Snapshot Date],'02_Control_Panel'!$B$5) -> 192 | I11: =SUMIFS(tblInventory[Stock Value],tblInventory[Distributor ID],A11,tblInventory[Snapshot Date],'02_Control_Panel'!$B$5) -> 413450 | J11: =SUMIFS(tblCollections[Outstanding Amount],tblCollections[Distributor ID],A11) -> 712000 | K11: =IF(J11=0,"Paid",IF(J11>0,"Outstanding","Review")) -> Outstanding | L11: =IF(COUNTIFS(tblInventory[Distributor ID],A11,tblInventory[Snapshot Date],'02_Control_Panel'!$B$5,tblInventory[Stock Status],"High Stock")>0,"High Stock","Normal") -> High Stock | M11: =IF(AND(L11="High Stock",E11>0),"Potential Slow-Moving","Normal") -> Potential Slow-Moving
A12: D009 | B12: =IFERROR(INDEX(tblDistributors[Distributor Name],MATCH(A12,tblDistributors[Distributor ID],0)),"") -> Capital Wholesale Network | C12: =IFERROR(INDEX(tblDistributors[City ID],MATCH(A12,tblDistributors[Distributor ID],0)),"") -> C003 | D12: =IFERROR(INDEX(tblDistributors[Salesperson ID],MATCH(A12,tblDistributors[Distributor ID],0)),"") -> SP009 | E12: =SUMIFS(tblSalesTransactions[Sales Amount],tblSalesTransactions[Distributor ID],A12) -> 4437750 | F12: =COUNTIFS(tblSalesTransactions[Distributor ID],A12) -> 25 | G12: =IFERROR(E12/F12,0) -> 177510 | H12: =SUMIFS(tblInventory[Closing Stock Qty],tblInventory[Distributor ID],A12,tblInventory[Snapshot Date],'02_Control_Panel'!$B$5) -> 144 | I12: =SUMIFS(tblInventory[Stock Value],tblInventory[Distributor ID],A12,tblInventory[Snapshot Date],'02_Control_Panel'!$B$5) -> 252650 | J12: =SUMIFS(tblCollections[Outstanding Amount],tblCollections[Distributor ID],A12) -> 112000 | K12: =IF(J12=0,"Paid",IF(J12>0,"Outstanding","Review")) -> Outstanding | L12: =IF(COUNTIFS(tblInventory[Distributor ID],A12,tblInventory[Snapshot Date],'02_Control_Panel'!$B$5,tblInventory[Stock Status],"High Stock")>0,"High Stock","Normal") -> Normal | M12: =IF(AND(L12="High Stock",E12>0),"Potential Slow-Moving","Normal") -> Normal
A13: D010 | B13: =IFERROR(INDEX(tblDistributors[Distributor Name],MATCH(A13,tblDistributors[Distributor ID],0)),"") -> Rawalpindi Distribution Co. | C13: =IFERROR(INDEX(tblDistributors[City ID],MATCH(A13,tblDistributors[Distributor ID],0)),"") -> C004 | D13: =IFERROR(INDEX(tblDistributors[Salesperson ID],MATCH(A13,tblDistributors[Distributor ID],0)),"") -> SP010 | E13: =SUMIFS(tblSalesTransactions[Sales Amount],tblSalesTransactions[Distributor ID],A13) -> 3992000 | F13: =COUNTIFS(tblSalesTransactions[Distributor ID],A13) -> 25 | G13: =IFERROR(E13/F13,0) -> 159680 | H13: =SUMIFS(tblInventory[Closing Stock Qty],tblInventory[Distributor ID],A13,tblInventory[Snapshot Date],'02_Control_Panel'!$B$5) -> 152 | I13: =SUMIFS(tblInventory[Stock Value],tblInventory[Distributor ID],A13,tblInventory[Snapshot Date],'02_Control_Panel'!$B$5) -> 307900 | J13: =SUMIFS(tblCollections[Outstanding Amount],tblCollections[Distributor ID],A13) -> 165000 | K13: =IF(J13=0,"Paid",IF(J13>0,"Outstanding","Review")) -> Outstanding | L13: =IF(COUNTIFS(tblInventory[Distributor ID],A13,tblInventory[Snapshot Date],'02_Control_Panel'!$B$5,tblInventory[Stock Status],"High Stock")>0,"High Stock","Normal") -> Normal | M13: =IF(AND(L13="High Stock",E13>0),"Potential Slow-Moving","Normal") -> Normal
A14: D011 | B14: =IFERROR(INDEX(tblDistributors[Distributor Name],MATCH(A14,tblDistributors[Distributor ID],0)),"") -> Potohar Trade House | C14: =IFERROR(INDEX(tblDistributors[City ID],MATCH(A14,tblDistributors[Distributor ID],0)),"") -> C004 | D14: =IFERROR(INDEX(tblDistributors[Salesperson ID],MATCH(A14,tblDistributors[Distributor ID],0)),"") -> SP011 | E14: =SUMIFS(tblSalesTransactions[Sales Amount],tblSalesTransactions[Distributor ID],A14) -> 4153250 | F14: =COUNTIFS(tblSalesTransactions[Distributor ID],A14) -> 25 | G14: =IFERROR(E14/F14,0) -> 166130 | H14: =SUMIFS(tblInventory[Closing Stock Qty],tblInventory[Distributor ID],A14,tblInventory[Snapshot Date],'02_Control_Panel'!$B$5) -> 135 | I14: =SUMIFS(tblInventory[Stock Value],tblInventory[Distributor ID],A14,tblInventory[Snapshot Date],'02_Control_Panel'!$B$5) -> 214850 | J14: =SUMIFS(tblCollections[Outstanding Amount],tblCollections[Distributor ID],A14) -> 547000 | K14: =IF(J14=0,"Paid",IF(J14>0,"Outstanding","Review")) -> Outstanding | L14: =IF(COUNTIFS(tblInventory[Distributor ID],A14,tblInventory[Snapshot Date],'02_Control_Panel'!$B$5,tblInventory[Stock Status],"High Stock")>0,"High Stock","Normal") -> Normal | M14: =IF(AND(L14="High Stock",E14>0),"Potential Slow-Moving","Normal") -> Normal
A15: D012 | B15: =IFERROR(INDEX(tblDistributors[Distributor Name],MATCH(A15,tblDistributors[Distributor ID],0)),"") -> Rawalpindi Wholesale Mart | C15: =IFERROR(INDEX(tblDistributors[City ID],MATCH(A15,tblDistributors[Distributor ID],0)),"") -> C004 | D15: =IFERROR(INDEX(tblDistributors[Salesperson ID],MATCH(A15,tblDistributors[Distributor ID],0)),"") -> SP012 | E15: =SUMIFS(tblSalesTransactions[Sales Amount],tblSalesTransactions[Distributor ID],A15) -> 3855750 | F15: =COUNTIFS(tblSalesTransactions[Distributor ID],A15) -> 25 | G15: =IFERROR(E15/F15,0) -> 154230 | H15: =SUMIFS(tblInventory[Closing Stock Qty],tblInventory[Distributor ID],A15,tblInventory[Snapshot Date],'02_Control_Panel'!$B$5) -> 144 | I15: =SUMIFS(tblInventory[Stock Value],tblInventory[Distributor ID],A15,tblInventory[Snapshot Date],'02_Control_Panel'!$B$5) -> 212700 | J15: =SUMIFS(tblCollections[Outstanding Amount],tblCollections[Distributor ID],A15) -> 243000 | K15: =IF(J15=0,"Paid",IF(J15>0,"Outstanding","Review")) -> Outstanding | L15: =IF(COUNTIFS(tblInventory[Distributor ID],A15,tblInventory[Snapshot Date],'02_Control_Panel'!$B$5,tblInventory[Stock Status],"High Stock")>0,"High Stock","Normal") -> Normal | M15: =IF(AND(L15="High Stock",E15>0),"Potential Slow-Moving","Normal") -> Normal
E16: =SUBTOTAL(109,tblDistributorAnalysis[Total Sales]) -> 60255750 | H16: =SUBTOTAL(109,tblDistributorAnalysis[Closing Stock Qty]) -> 2128 | I16: =SUBTOTAL(109,tblDistributorAnalysis[Stock Value]) -> 3553500 | J16: =SUBTOTAL(109,tblDistributorAnalysis[Outstanding Amount]) -> 2654000

Sheet 15_Product_Analysis
A1: Product Analysis
A3: Product ID | B3: Product Name | C3: Brand | D3: Category | E3: Total Quantity Sold | F3: Total Sales | G3: Transaction Count | H3: Average Selling Price | I3: Closing Distributor Stock Qty | J3: Distributor Stock Value | K3: Sales Contribution % | L3: Approx. Months of Distributor Stock | M3: Sales Rank | O3: Top 10 Products by Sales | R3: Product KPI Summary
A4: P001 | B4: =IFERROR(INDEX(tblProducts[Product Name],MATCH(A4,tblProducts[Product ID],0)),"") -> Corn Flakes Original | C4: =IFERROR(INDEX(tblProducts[Brand],MATCH(A4,tblProducts[Product ID],0)),"") -> Morning Harvest | D4: =IFERROR(INDEX(tblProducts[Category],MATCH(A4,tblProducts[Product ID],0)),"") -> Morning Cereals | E4: =SUMIFS(tblSalesTransactions[Quantity],tblSalesTransactions[Product ID],A4) -> 1840 | F4: =SUMIFS(tblSalesTransactions[Sales Amount],tblSalesTransactions[Product ID],A4) -> 1564000 | G4: =COUNTIFS(tblSalesTransactions[Product ID],A4) -> 12 | H4: =IFERROR(F4/E4,0) -> 850 | I4: =SUMIFS(tblInventory[Closing Stock Qty],tblInventory[Product ID],A4,tblInventory[Snapshot Date],DATE(2026,12,31)) -> 141 | J4: =SUMIFS(tblInventory[Stock Value],tblInventory[Product ID],A4,tblInventory[Snapshot Date],DATE(2026,12,31)) -> 119850 | K4: =IFERROR(F4/SUM(tblProductAnalysis[Total Sales]),0) -> 0.025956029 | L4: =IFERROR(I4/(E4/12),0) -> 0.91956522 | M4: =RANK(F4,$F$4:$F$59,0)+COUNTIF($F$4:F4,F4)-1 -> 20 | O4: Product ID | P4: Product Name | Q4: Total Sales | R4: Total Products | S4: =COUNTA(tblProductAnalysis[Product ID]) -> 56
A5: P002 | B5: =IFERROR(INDEX(tblProducts[Product Name],MATCH(A5,tblProducts[Product ID],0)),"") -> Corn Flakes Original | C5: =IFERROR(INDEX(tblProducts[Brand],MATCH(A5,tblProducts[Product ID],0)),"") -> Morning Harvest | D5: =IFERROR(INDEX(tblProducts[Category],MATCH(A5,tblProducts[Product ID],0)),"") -> Morning Cereals | E5: =SUMIFS(tblSalesTransactions[Quantity],tblSalesTransactions[Product ID],A5) -> 350 | F5: =SUMIFS(tblSalesTransactions[Sales Amount],tblSalesTransactions[Product ID],A5) -> 507500 | G5: =COUNTIFS(tblSalesTransactions[Product ID],A5) -> 3 | H5: =IFERROR(F5/E5,0) -> 1450 | I5: =SUMIFS(tblInventory[Closing Stock Qty],tblInventory[Product ID],A5,tblInventory[Snapshot Date],DATE(2026,12,31)) -> 56 | J5: =SUMIFS(tblInventory[Stock Value],tblInventory[Product ID],A5,tblInventory[Snapshot Date],DATE(2026,12,31)) -> 81200 | K5: =IFERROR(F5/SUM(tblProductAnalysis[Total Sales]),0) -> 0.0084224327 | L5: =IFERROR(I5/(E5/12),0) -> 1.92 | M5: =RANK(F5,$F$4:$F$59,0)+COUNTIF($F$4:F5,F5)-1 -> 30 | O5: =IFERROR(INDEX($A$4:$A$59,MATCH(ROWS($O$5:O5),$M$4:$M$59,0)),"") -> P038 | P5: =IFERROR(INDEX($B$4:$B$59,MATCH(ROWS($P$5:P5),$M$4:$M$59,0)),"") -> Pandoro Classico | Q5: =IFERROR(INDEX($F$4:$F$59,MATCH(ROWS($Q$5:Q5),$M$4:$M$59,0)),0) -> 4060000 | R5: Total Quantity Sold | S5: =SUM(tblProductAnalysis[Total Quantity Sold]) -> 38025
A6: P003 | B6: =IFERROR(INDEX(tblProducts[Product Name],MATCH(A6,tblProducts[Product ID],0)),"") -> Corn Flakes Original | C6: =IFERROR(INDEX(tblProducts[Brand],MATCH(A6,tblProducts[Product ID],0)),"") -> Morning Harvest | D6: =IFERROR(INDEX(tblProducts[Category],MATCH(A6,tblProducts[Product ID],0)),"") -> Morning Cereals | E6: =SUMIFS(tblSalesTransactions[Quantity],tblSalesTransactions[Product ID],A6) -> 1495 | F6: =SUMIFS(tblSalesTransactions[Sales Amount],tblSalesTransactions[Product ID],A6) -> 4036500 | G6: =COUNTIFS(tblSalesTransactions[Product ID],A6) -> 12 | H6: =IFERROR(F6/E6,0) -> 2700 | I6: =SUMIFS(tblInventory[Closing Stock Qty],tblInventory[Product ID],A6,tblInventory[Snapshot Date],DATE(2026,12,31)) -> 58 | J6: =SUMIFS(tblInventory[Stock Value],tblInventory[Product ID],A6,tblInventory[Snapshot Date],DATE(2026,12,31)) -> 84100 | K6: =IFERROR(F6/SUM(tblProductAnalysis[Total Sales]),0) -> 0.066989457 | L6: =IFERROR(I6/(E6/12),0) -> 0.46555184 | M6: =RANK(F6,$F$4:$F$59,0)+COUNTIF($F$4:F6,F6)-1 -> 2 | O6: =IFERROR(INDEX($A$4:$A$59,MATCH(ROWS($O$5:O6),$M$4:$M$59,0)),"") -> P003 | P6: =IFERROR(INDEX($B$4:$B$59,MATCH(ROWS($P$5:P6),$M$4:$M$59,0)),"") -> Corn Flakes Original | Q6: =IFERROR(INDEX($F$4:$F$59,MATCH(ROWS($Q$5:Q6),$M$4:$M$59,0)),0) -> 4036500 | R6: Total Sales | S6: =SUM(tblProductAnalysis[Total Sales]) -> 60255750
A7: P004 | B7: =IFERROR(INDEX(tblProducts[Product Name],MATCH(A7,tblProducts[Product ID],0)),"") -> Honey Corn Flakes | C7: =IFERROR(INDEX(tblProducts[Brand],MATCH(A7,tblProducts[Product ID],0)),"") -> Morning Harvest | D7: =IFERROR(INDEX(tblProducts[Category],MATCH(A7,tblProducts[Product ID],0)),"") -> Morning Cereals | E7: =SUMIFS(tblSalesTransactions[Quantity],tblSalesTransactions[Product ID],A7) -> 2015 | F7: =SUMIFS(tblSalesTransactions[Sales Amount],tblSalesTransactions[Product ID],A7) -> 1813500 | G7: =COUNTIFS(tblSalesTransactions[Product ID],A7) -> 12 | H7: =IFERROR(F7/E7,0) -> 900 | I7: =SUMIFS(tblInventory[Closing Stock Qty],tblInventory[Product ID],A7,tblInventory[Snapshot Date],DATE(2026,12,31)) -> 116 | J7: =SUMIFS(tblInventory[Stock Value],tblInventory[Product ID],A7,tblInventory[Snapshot Date],DATE(2026,12,31)) -> 104400 | K7: =IFERROR(F7/SUM(tblProductAnalysis[Total Sales]),0) -> 0.030096713 | L7: =IFERROR(I7/(E7/12),0) -> 0.69081886 | M7: =RANK(F7,$F$4:$F$59,0)+COUNTIF($F$4:F7,F7)-1 -> 18 | O7: =IFERROR(INDEX($A$4:$A$59,MATCH(ROWS($O$5:O7),$M$4:$M$59,0)),"") -> P036 | P7: =IFERROR(INDEX($B$4:$B$59,MATCH(ROWS($P$5:P7),$M$4:$M$59,0)),"") -> Chocolate Panettone | Q7: =IFERROR(INDEX($F$4:$F$59,MATCH(ROWS($Q$5:Q7),$M$4:$M$59,0)),0) -> 3712500 | R7: Total Distributor Stock Value | S7: =SUM(tblProductAnalysis[Distributor Stock Value]) -> 3553500
A8: P005 | B8: =IFERROR(INDEX(tblProducts[Product Name],MATCH(A8,tblProducts[Product ID],0)),"") -> Honey Corn Flakes | C8: =IFERROR(INDEX(tblProducts[Brand],MATCH(A8,tblProducts[Product ID],0)),"") -> Morning Harvest | D8: =IFERROR(INDEX(tblProducts[Category],MATCH(A8,tblProducts[Product ID],0)),"") -> Morning Cereals | E8: =SUMIFS(tblSalesTransactions[Quantity],tblSalesTransactions[Product ID],A8) -> 2005 | F8: =SUMIFS(tblSalesTransactions[Sales Amount],tblSalesTransactions[Product ID],A8) -> 1904750 | G8: =COUNTIFS(tblSalesTransactions[Product ID],A8) -> 13 | H8: =IFERROR(F8/E8,0) -> 950 | I8: =SUMIFS(tblInventory[Closing Stock Qty],tblInventory[Product ID],A8,tblInventory[Snapshot Date],DATE(2026,12,31)) -> 51 | J8: =SUMIFS(tblInventory[Stock Value],tblInventory[Product ID],A8,tblInventory[Snapshot Date],DATE(2026,12,31)) -> 48450 | K8: =IFERROR(F8/SUM(tblProductAnalysis[Total Sales]),0) -> 0.031611091 | L8: =IFERROR(I8/(E8/12),0) -> 0.30523691 | M8: =RANK(F8,$F$4:$F$59,0)+COUNTIF($F$4:F8,F8)-1 -> 15 | O8: =IFERROR(INDEX($A$4:$A$59,MATCH(ROWS($O$5:O8),$M$4:$M$59,0)),"") -> P032 | P8: =IFERROR(INDEX($B$4:$B$59,MATCH(ROWS($P$5:P8),$M$4:$M$59,0)),"") -> Classic Panettone | Q8: =IFERROR(INDEX($F$4:$F$59,MATCH(ROWS($Q$5:Q8),$M$4:$M$59,0)),0) -> 3487000
A9: P006 | B9: =IFERROR(INDEX(tblProducts[Product Name],MATCH(A9,tblProducts[Product ID],0)),"") -> Chocolate Corn Flakes | C9: =IFERROR(INDEX(tblProducts[Brand],MATCH(A9,tblProducts[Product ID],0)),"") -> Morning Harvest | D9: =IFERROR(INDEX(tblProducts[Category],MATCH(A9,tblProducts[Product ID],0)),"") -> Morning Cereals | E9: =SUMIFS(tblSalesTransactions[Quantity],tblSalesTransactions[Product ID],A9) -> 650 | F9: =SUMIFS(tblSalesTransactions[Sales Amount],tblSalesTransactions[Product ID],A9) -> 747500 | G9: =COUNTIFS(tblSalesTransactions[Product ID],A9) -> 6 | H9: =IFERROR(F9/E9,0) -> 1150 | I9: =SUMIFS(tblInventory[Closing Stock Qty],tblInventory[Product ID],A9,tblInventory[Snapshot Date],DATE(2026,12,31)) -> 54 | J9: =SUMIFS(tblInventory[Stock Value],tblInventory[Product ID],A9,tblInventory[Snapshot Date],DATE(2026,12,31)) -> 62100 | K9: =IFERROR(F9/SUM(tblProductAnalysis[Total Sales]),0) -> 0.012405455 | L9: =IFERROR(I9/(E9/12),0) -> 0.99692308 | M9: =RANK(F9,$F$4:$F$59,0)+COUNTIF($F$4:F9,F9)-1 -> 28 | O9: =IFERROR(INDEX($A$4:$A$59,MATCH(ROWS($O$5:O9),$M$4:$M$59,0)),"") -> P035 | P9: =IFERROR(INDEX($B$4:$B$59,MATCH(ROWS($P$5:P9),$M$4:$M$59,0)),"") -> Chocolate Panettone | Q9: =IFERROR(INDEX($F$4:$F$59,MATCH(ROWS($Q$5:Q9),$M$4:$M$59,0)),0) -> 3240000
A10: P007 | B10: =IFERROR(INDEX(tblProducts[Product Name],MATCH(A10,tblProducts[Product ID],0)),"") -> Chocolate Corn Flakes | C10: =IFERROR(INDEX(tblProducts[Brand],MATCH(A10,tblProducts[Product ID],0)),"") -> Morning Harvest | D10: =IFERROR(INDEX(tblProducts[Category],MATCH(A10,tblProducts[Product ID],0)),"") -> Morning Cereals | E10: =SUMIFS(tblSalesTransactions[Quantity],tblSalesTransactions[Product ID],A10) -> 705 | F10: =SUMIFS(tblSalesTransactions[Sales Amount],tblSalesTransactions[Product ID],A10) -> 846000 | G10: =COUNTIFS(tblSalesTransactions[Product ID],A10) -> 6 | H10: =IFERROR(F10/E10,0) -> 1200 | I10: =SUMIFS(tblInventory[Closing Stock Qty],tblInventory[Product ID],A10,tblInventory[Snapshot Date],DATE(2026,12,31)) -> 49 | J10: =SUMIFS(tblInventory[Stock Value],tblInventory[Product ID],A10,tblInventory[Snapshot Date],DATE(2026,12,31)) -> 58800 | K10: =IFERROR(F10/SUM(tblProductAnalysis[Total Sales]),0) -> 0.014040154 | L10: =IFERROR(I10/(E10/12),0) -> 0.83404255 | M10: =RANK(F10,$F$4:$F$59,0)+COUNTIF($F$4:F10,F10)-1 -> 26 | O10: =IFERROR(INDEX($A$4:$A$59,MATCH(ROWS($O$5:O10),$M$4:$M$59,0)),"") -> P015 | P10: =IFERROR(INDEX($B$4:$B$59,MATCH(ROWS($P$5:P10),$M$4:$M$59,0)),"") -> Muesli Classic | Q10: =IFERROR(INDEX($F$4:$F$59,MATCH(ROWS($Q$5:Q10),$M$4:$M$59,0)),0) -> 3198000
A11: P008 | B11: =IFERROR(INDEX(tblProducts[Product Name],MATCH(A11,tblProducts[Product ID],0)),"") -> Frosted Flakes | C11: =IFERROR(INDEX(tblProducts[Brand],MATCH(A11,tblProducts[Product ID],0)),"") -> Morning Harvest | D11: =IFERROR(INDEX(tblProducts[Category],MATCH(A11,tblProducts[Product ID],0)),"") -> Morning Cereals | E11: =SUMIFS(tblSalesTransactions[Quantity],tblSalesTransactions[Product ID],A11) -> 1575 | F11: =SUMIFS(tblSalesTransactions[Sales Amount],tblSalesTransactions[Product ID],A11) -> 1732500 | G11: =COUNTIFS(tblSalesTransactions[Product ID],A11) -> 12 | H11: =IFERROR(F11/E11,0) -> 1100 | I11: =SUMIFS(tblInventory[Closing Stock Qty],tblInventory[Product ID],A11,tblInventory[Snapshot Date],DATE(2026,12,31)) -> 50 | J11: =SUMIFS(tblInventory[Stock Value],tblInventory[Product ID],A11,tblInventory[Snapshot Date],DATE(2026,12,31)) -> 60000 | K11: =IFERROR(F11/SUM(tblProductAnalysis[Total Sales]),0) -> 0.028752443 | L11: =IFERROR(I11/(E11/12),0) -> 0.38095238 | M11: =RANK(F11,$F$4:$F$59,0)+COUNTIF($F$4:F11,F11)-1 -> 19 | O11: =IFERROR(INDEX($A$4:$A$59,MATCH(ROWS($O$5:O11),$M$4:$M$59,0)),"") -> P021 | P11: =IFERROR(INDEX($B$4:$B$59,MATCH(ROWS($P$5:P11),$M$4:$M$59,0)),"") -> Granola Honey | Q11: =IFERROR(INDEX($F$4:$F$59,MATCH(ROWS($Q$5:Q11),$M$4:$M$59,0)),0) -> 2904000
A12: P009 | B12: =IFERROR(INDEX(tblProducts[Product Name],MATCH(A12,tblProducts[Product ID],0)),"") -> Frosted Flakes | C12: =IFERROR(INDEX(tblProducts[Brand],MATCH(A12,tblProducts[Product ID],0)),"") -> Morning Harvest | D12: =IFERROR(INDEX(tblProducts[Category],MATCH(A12,tblProducts[Product ID],0)),"") -> Morning Cereals | E12: =SUMIFS(tblSalesTransactions[Quantity],tblSalesTransactions[Product ID],A12) -> 0 | F12: =SUMIFS(tblSalesTransactions[Sales Amount],tblSalesTransactions[Product ID],A12) -> 0 | G12: =COUNTIFS(tblSalesTransactions[Product ID],A12) -> 0 | H12: =IFERROR(F12/E12,0) -> 0 | I12: =SUMIFS(tblInventory[Closing Stock Qty],tblInventory[Product ID],A12,tblInventory[Snapshot Date],DATE(2026,12,31)) -> 48 | J12: =SUMIFS(tblInventory[Stock Value],tblInventory[Product ID],A12,tblInventory[Snapshot Date],DATE(2026,12,31)) -> 57600 | K12: =IFERROR(F12/SUM(tblProductAnalysis[Total Sales]),0) -> 0 | L12: =IFERROR(I12/(E12/12),0) -> 0 | M12: =RANK(F12,$F$4:$F$59,0)+COUNTIF($F$4:F12,F12)-1 -> 36 | O12: =IFERROR(INDEX($A$4:$A$59,MATCH(ROWS($O$5:O12),$M$4:$M$59,0)),"") -> P049 | P12: =IFERROR(INDEX($B$4:$B$59,MATCH(ROWS($P$5:P12),$M$4:$M$59,0)),"") -> Mini Croissant Classic | Q12: =IFERROR(INDEX($F$4:$F$59,MATCH(ROWS($Q$5:Q12),$M$4:$M$59,0)),0) -> 2519000
A13: P010 | B13: =IFERROR(INDEX(tblProducts[Product Name],MATCH(A13,tblProducts[Product ID],0)),"") -> Bran Flakes | C13: =IFERROR(INDEX(tblProducts[Brand],MATCH(A13,tblProducts[Product ID],0)),"") -> Morning Harvest | D13: =IFERROR(INDEX(tblProducts[Category],MATCH(A13,tblProducts[Product ID],0)),"") -> Morning Cereals | E13: =SUMIFS(tblSalesTransactions[Quantity],tblSalesTransactions[Product ID],A13) -> 0 | F13: =SUMIFS(tblSalesTransactions[Sales Amount],tblSalesTransactions[Product ID],A13) -> 0 | G13: =COUNTIFS(tblSalesTransactions[Product ID],A13) -> 0 | H13: =IFERROR(F13/E13,0) -> 0 | I13: =SUMIFS(tblInventory[Closing Stock Qty],tblInventory[Product ID],A13,tblInventory[Snapshot Date],DATE(2026,12,31)) -> 54 | J13: =SUMIFS(tblInventory[Stock Value],tblInventory[Product ID],A13,tblInventory[Snapshot Date],DATE(2026,12,31)) -> 78300 | K13: =IFERROR(F13/SUM(tblProductAnalysis[Total Sales]),0) -> 0 | L13: =IFERROR(I13/(E13/12),0) -> 0 | M13: =RANK(F13,$F$4:$F$59,0)+COUNTIF($F$4:F13,F13)-1 -> 37 | O13: =IFERROR(INDEX($A$4:$A$59,MATCH(ROWS($O$5:O13),$M$4:$M$59,0)),"") -> P042 | P13: =IFERROR(INDEX($B$4:$B$59,MATCH(ROWS($P$5:P13),$M$4:$M$59,0)),"") -> Chocolate Cake | Q13: =IFERROR(INDEX($F$4:$F$59,MATCH(ROWS($Q$5:Q13),$M$4:$M$59,0)),0) -> 2385000
A14: P011 | B14: =IFERROR(INDEX(tblProducts[Product Name],MATCH(A14,tblProducts[Product ID],0)),"") -> Bran Flakes | C14: =IFERROR(INDEX(tblProducts[Brand],MATCH(A14,tblProducts[Product ID],0)),"") -> Morning Harvest | D14: =IFERROR(INDEX(tblProducts[Category],MATCH(A14,tblProducts[Product ID],0)),"") -> Morning Cereals | E14: =SUMIFS(tblSalesTransactions[Quantity],tblSalesTransactions[Product ID],A14) -> 0 | F14: =SUMIFS(tblSalesTransactions[Sales Amount],tblSalesTransactions[Product ID],A14) -> 0 | G14: =COUNTIFS(tblSalesTransactions[Product ID],A14) -> 0 | H14: =IFERROR(F14/E14,0) -> 0 | I14: =SUMIFS(tblInventory[Closing Stock Qty],tblInventory[Product ID],A14,tblInventory[Snapshot Date],DATE(2026,12,31)) -> 0 | J14: =SUMIFS(tblInventory[Stock Value],tblInventory[Product ID],A14,tblInventory[Snapshot Date],DATE(2026,12,31)) -> 0 | K14: =IFERROR(F14/SUM(tblProductAnalysis[Total Sales]),0) -> 0 | L14: =IFERROR(I14/(E14/12),0) -> 0 | M14: =RANK(F14,$F$4:$F$59,0)+COUNTIF($F$4:F14,F14)-1 -> 38 | O14: =IFERROR(INDEX($A$4:$A$59,MATCH(ROWS($O$5:O14),$M$4:$M$59,0)),"") -> P041 | P14: =IFERROR(INDEX($B$4:$B$59,MATCH(ROWS($P$5:P14),$M$4:$M$59,0)),"") -> Chocolate Cake | Q14: =IFERROR(INDEX($F$4:$F$59,MATCH(ROWS($Q$5:Q14),$M$4:$M$59,0)),0) -> 2212500
A15: P012 | B15: =IFERROR(INDEX(tblProducts[Product Name],MATCH(A15,tblProducts[Product ID],0)),"") -> High Fibre Cereal | C15: =IFERROR(INDEX(tblProducts[Brand],MATCH(A15,tblProducts[Product ID],0)),"") -> Morning Harvest | D15: =IFERROR(INDEX(tblProducts[Category],MATCH(A15,tblProducts[Product ID],0)),"") -> Morning Cereals | E15: =SUMIFS(tblSalesTransactions[Quantity],tblSalesTransactions[Product ID],A15) -> 0 | F15: =SUMIFS(tblSalesTransactions[Sales Amount],tblSalesTransactions[Product ID],A15) -> 0 | G15: =COUNTIFS(tblSalesTransactions[Product ID],A15) -> 0 | H15: =IFERROR(F15/E15,0) -> 0 | I15: =SUMIFS(tblInventory[Closing Stock Qty],tblInventory[Product ID],A15,tblInventory[Snapshot Date],DATE(2026,12,31)) -> 0 | J15: =SUMIFS(tblInventory[Stock Value],tblInventory[Product ID],A15,tblInventory[Snapshot Date],DATE(2026,12,31)) -> 0 | K15: =IFERROR(F15/SUM(tblProductAnalysis[Total Sales]),0) -> 0 | L15: =IFERROR(I15/(E15/12),0) -> 0 | M15: =RANK(F15,$F$4:$F$59,0)+COUNTIF($F$4:F15,F15)-1 -> 39
A16: P013 | B16: =IFERROR(INDEX(tblProducts[Product Name],MATCH(A16,tblProducts[Product ID],0)),"") -> High Fibre Cereal | C16: =IFERROR(INDEX(tblProducts[Brand],MATCH(A16,tblProducts[Product ID],0)),"") -> Morning Harvest | D16: =IFERROR(INDEX(tblProducts[Category],MATCH(A16,tblProducts[Product ID],0)),"") -> Morning Cereals | E16: =SUMIFS(tblSalesTransactions[Quantity],tblSalesTransactions[Product ID],A16) -> 0 | F16: =SUMIFS(tblSalesTransactions[Sales Amount],tblSalesTransactions[Product ID],A16) -> 0 | G16: =COUNTIFS(tblSalesTransactions[Product ID],A16) -> 0 | H16: =IFERROR(F16/E16,0) -> 0 | I16: =SUMIFS(tblInventory[Closing Stock Qty],tblInventory[Product ID],A16,tblInventory[Snapshot Date],DATE(2026,12,31)) -> 0 | J16: =SUMIFS(tblInventory[Stock Value],tblInventory[Product ID],A16,tblInventory[Snapshot Date],DATE(2026,12,31)) -> 0 | K16: =IFERROR(F16/SUM(tblProductAnalysis[Total Sales]),0) -> 0 | L16: =IFERROR(I16/(E16/12),0) -> 0 | M16: =RANK(F16,$F$4:$F$59,0)+COUNTIF($F$4:F16,F16)-1 -> 40
A17: P014 | B17: =IFERROR(INDEX(tblProducts[Product Name],MATCH(A17,tblProducts[Product ID],0)),"") -> Muesli Classic | C17: =IFERROR(INDEX(tblProducts[Brand],MATCH(A17,tblProducts[Product ID],0)),"") -> Morning Harvest | D17: =IFERROR(INDEX(tblProducts[Category],MATCH(A17,tblProducts[Product ID],0)),"") -> Morning Cereals | E17: =SUMIFS(tblSalesTransactions[Quantity],tblSalesTransactions[Product ID],A17) -> 1270 | F17: =SUMIFS(tblSalesTransactions[Sales Amount],tblSalesTransactions[Product ID],A17) -> 1841500 | G17: =COUNTIFS(tblSalesTransactions[Product ID],A17) -> 12 | H17: =IFERROR(F17/E17,0) -> 1450 | I17: =SUMIFS(tblInventory[Closing Stock Qty],tblInventory[Product ID],A17,tblInventory[Snapshot Date],DATE(2026,12,31)) -> 233 | J17: =SUMIFS(tblInventory[Stock Value],tblInventory[Product ID],A17,tblInventory[Snapshot Date],DATE(2026,12,31)) -> 337850 | K17: =IFERROR(F17/SUM(tblProductAnalysis[Total Sales]),0) -> 0.030561399 | L17: =IFERROR(I17/(E17/12),0) -> 2.2015748 | M17: =RANK(F17,$F$4:$F$59,0)+COUNTIF($F$4:F17,F17)-1 -> 16
A18: P015 | B18: =IFERROR(INDEX(tblProducts[Product Name],MATCH(A18,tblProducts[Product ID],0)),"") -> Muesli Classic | C18: =IFERROR(INDEX(tblProducts[Brand],MATCH(A18,tblProducts[Product ID],0)),"") -> Morning Harvest | D18: =IFERROR(INDEX(tblProducts[Category],MATCH(A18,tblProducts[Product ID],0)),"") -> Morning Cereals | E18: =SUMIFS(tblSalesTransactions[Quantity],tblSalesTransactions[Product ID],A18) -> 1230 | F18: =SUMIFS(tblSalesTransactions[Sales Amount],tblSalesTransactions[Product ID],A18) -> 3198000 | G18: =COUNTIFS(tblSalesTransactions[Product ID],A18) -> 12 | H18: =IFERROR(F18/E18,0) -> 2600 | I18: =SUMIFS(tblInventory[Closing Stock Qty],tblInventory[Product ID],A18,tblInventory[Snapshot Date],DATE(2026,12,31)) -> 76 | J18: =SUMIFS(tblInventory[Stock Value],tblInventory[Product ID],A18,tblInventory[Snapshot Date],DATE(2026,12,31)) -> 197600 | K18: =IFERROR(F18/SUM(tblProductAnalysis[Total Sales]),0) -> 0.053073773 | L18: =IFERROR(I18/(E18/12),0) -> 0.74146341 | M18: =RANK(F18,$F$4:$F$59,0)+COUNTIF($F$4:F18,F18)-1 -> 6
A19: P016 | B19: =IFERROR(INDEX(tblProducts[Product Name],MATCH(A19,tblProducts[Product ID],0)),"") -> Fruit & Nut Muesli | C19: =IFERROR(INDEX(tblProducts[Brand],MATCH(A19,tblProducts[Product ID],0)),"") -> Morning Harvest | D19: =IFERROR(INDEX(tblProducts[Category],MATCH(A19,tblProducts[Product ID],0)),"") -> Morning Cereals | E19: =SUMIFS(tblSalesTransactions[Quantity],tblSalesTransactions[Product ID],A19) -> 180 | F19: =SUMIFS(tblSalesTransactions[Sales Amount],tblSalesTransactions[Product ID],A19) -> 297000 | G19: =COUNTIFS(tblSalesTransactions[Product ID],A19) -> 2 | H19: =IFERROR(F19/E19,0) -> 1650 | I19: =SUMIFS(tblInventory[Closing Stock Qty],tblInventory[Product ID],A19,tblInventory[Snapshot Date],DATE(2026,12,31)) -> 35 | J19: =SUMIFS(tblInventory[Stock Value],tblInventory[Product ID],A19,tblInventory[Snapshot Date],DATE(2026,12,31)) -> 52500 | K19: =IFERROR(F19/SUM(tblProductAnalysis[Total Sales]),0) -> 0.0049289902 | L19: =IFERROR(I19/(E19/12),0) -> 2.3333333 | M19: =RANK(F19,$F$4:$F$59,0)+COUNTIF($F$4:F19,F19)-1 -> 32
A20: P017 | B20: =IFERROR(INDEX(tblProducts[Product Name],MATCH(A20,tblProducts[Product ID],0)),"") -> Fruit & Nut Muesli | C20: =IFERROR(INDEX(tblProducts[Brand],MATCH(A20,tblProducts[Product ID],0)),"") -> Morning Harvest | D20: =IFERROR(INDEX(tblProducts[Category],MATCH(A20,tblProducts[Product ID],0)),"") -> Morning Cereals | E20: =SUMIFS(tblSalesTransactions[Quantity],tblSalesTransactions[Product ID],A20) -> 75 | F20: =SUMIFS(tblSalesTransactions[Sales Amount],tblSalesTransactions[Product ID],A20) -> 135000 | G20: =COUNTIFS(tblSalesTransactions[Product ID],A20) -> 1 | H20: =IFERROR(F20/E20,0) -> 1800 | I20: =SUMIFS(tblInventory[Closing Stock Qty],tblInventory[Product ID],A20,tblInventory[Snapshot Date],DATE(2026,12,31)) -> 32 | J20: =SUMIFS(tblInventory[Stock Value],tblInventory[Product ID],A20,tblInventory[Snapshot Date],DATE(2026,12,31)) -> 83200 | K20: =IFERROR(F20/SUM(tblProductAnalysis[Total Sales]),0) -> 0.0022404501 | L20: =IFERROR(I20/(E20/12),0) -> 5.12 | M20: =RANK(F20,$F$4:$F$59,0)+COUNTIF($F$4:F20,F20)-1 -> 34
A21: P018 | B21: =IFERROR(INDEX(tblProducts[Product Name],MATCH(A21,tblProducts[Product ID],0)),"") -> Chocolate Muesli | C21: =IFERROR(INDEX(tblProducts[Brand],MATCH(A21,tblProducts[Product ID],0)),"") -> Morning Harvest | D21: =IFERROR(INDEX(tblProducts[Category],MATCH(A21,tblProducts[Product ID],0)),"") -> Morning Cereals | E21: =SUMIFS(tblSalesTransactions[Quantity],tblSalesTransactions[Product ID],A21) -> 510 | F21: =SUMIFS(tblSalesTransactions[Sales Amount],tblSalesTransactions[Product ID],A21) -> 969000 | G21: =COUNTIFS(tblSalesTransactions[Product ID],A21) -> 5 | H21: =IFERROR(F21/E21,0) -> 1900 | I21: =SUMIFS(tblInventory[Closing Stock Qty],tblInventory[Product ID],A21,tblInventory[Snapshot Date],DATE(2026,12,31)) -> 34 | J21: =SUMIFS(tblInventory[Stock Value],tblInventory[Product ID],A21,tblInventory[Snapshot Date],DATE(2026,12,31)) -> 71400 | K21: =IFERROR(F21/SUM(tblProductAnalysis[Total Sales]),0) -> 0.016081453 | L21: =IFERROR(I21/(E21/12),0) -> 0.8 | M21: =RANK(F21,$F$4:$F$59,0)+COUNTIF($F$4:F21,F21)-1 -> 23
A22: P019 | B22: =IFERROR(INDEX(tblProducts[Product Name],MATCH(A22,tblProducts[Product ID],0)),"") -> Chocolate Muesli | C22: =IFERROR(INDEX(tblProducts[Brand],MATCH(A22,tblProducts[Product ID],0)),"") -> Morning Harvest | D22: =IFERROR(INDEX(tblProducts[Category],MATCH(A22,tblProducts[Product ID],0)),"") -> Morning Cereals | E22: =SUMIFS(tblSalesTransactions[Quantity],tblSalesTransactions[Product ID],A22) -> 0 | F22: =SUMIFS(tblSalesTransactions[Sales Amount],tblSalesTransactions[Product ID],A22) -> 0 | G22: =COUNTIFS(tblSalesTransactions[Product ID],A22) -> 0 | H22: =IFERROR(F22/E22,0) -> 0 | I22: =SUMIFS(tblInventory[Closing Stock Qty],tblInventory[Product ID],A22,tblInventory[Snapshot Date],DATE(2026,12,31)) -> 36 | J22: =SUMIFS(tblInventory[Stock Value],tblInventory[Product ID],A22,tblInventory[Snapshot Date],DATE(2026,12,31)) -> 93600 | K22: =IFERROR(F22/SUM(tblProductAnalysis[Total Sales]),0) -> 0 | L22: =IFERROR(I22/(E22/12),0) -> 0 | M22: =RANK(F22,$F$4:$F$59,0)+COUNTIF($F$4:F22,F22)-1 -> 41
A23: P020 | B23: =IFERROR(INDEX(tblProducts[Product Name],MATCH(A23,tblProducts[Product ID],0)),"") -> Granola Honey | C23: =IFERROR(INDEX(tblProducts[Brand],MATCH(A23,tblProducts[Product ID],0)),"") -> Morning Harvest | D23: =IFERROR(INDEX(tblProducts[Category],MATCH(A23,tblProducts[Product ID],0)),"") -> Morning Cereals | E23: =SUMIFS(tblSalesTransactions[Quantity],tblSalesTransactions[Product ID],A23) -> 645 | F23: =SUMIFS(tblSalesTransactions[Sales Amount],tblSalesTransactions[Product ID],A23) -> 1161000 | G23: =COUNTIFS(tblSalesTransactions[Product ID],A23) -> 7 | H23: =IFERROR(F23/E23,0) -> 1800 | I23: =SUMIFS(tblInventory[Closing Stock Qty],tblInventory[Product ID],A23,tblInventory[Snapshot Date],DATE(2026,12,31)) -> 33 | J23: =SUMIFS(tblInventory[Stock Value],tblInventory[Product ID],A23,tblInventory[Snapshot Date],DATE(2026,12,31)) -> 59400 | K23: =IFERROR(F23/SUM(tblProductAnalysis[Total Sales]),0) -> 0.019267871 | L23: =IFERROR(I23/(E23/12),0) -> 0.61395349 | M23: =RANK(F23,$F$4:$F$59,0)+COUNTIF($F$4:F23,F23)-1 -> 21
A24: P021 | B24: =IFERROR(INDEX(tblProducts[Product Name],MATCH(A24,tblProducts[Product ID],0)),"") -> Granola Honey | C24: =IFERROR(INDEX(tblProducts[Brand],MATCH(A24,tblProducts[Product ID],0)),"") -> Morning Harvest | D24: =IFERROR(INDEX(tblProducts[Category],MATCH(A24,tblProducts[Product ID],0)),"") -> Morning Cereals | E24: =SUMIFS(tblSalesTransactions[Quantity],tblSalesTransactions[Product ID],A24) -> 1210 | F24: =SUMIFS(tblSalesTransactions[Sales Amount],tblSalesTransactions[Product ID],A24) -> 2904000 | G24: =COUNTIFS(tblSalesTransactions[Product ID],A24) -> 12 | H24: =IFERROR(F24/E24,0) -> 2400 | I24: =SUMIFS(tblInventory[Closing Stock Qty],tblInventory[Product ID],A24,tblInventory[Snapshot Date],DATE(2026,12,31)) -> 31 | J24: =SUMIFS(tblInventory[Stock Value],tblInventory[Product ID],A24,tblInventory[Snapshot Date],DATE(2026,12,31)) -> 74400 | K24: =IFERROR(F24/SUM(tblProductAnalysis[Total Sales]),0) -> 0.048194571 | L24: =IFERROR(I24/(E24/12),0) -> 0.30743802 | M24: =RANK(F24,$F$4:$F$59,0)+COUNTIF($F$4:F24,F24)-1 -> 7
A25: P022 | B25: =IFERROR(INDEX(tblProducts[Product Name],MATCH(A25,tblProducts[Product ID],0)),"") -> Granola Chocolate | C25: =IFERROR(INDEX(tblProducts[Brand],MATCH(A25,tblProducts[Product ID],0)),"") -> Morning Harvest | D25: =IFERROR(INDEX(tblProducts[Category],MATCH(A25,tblProducts[Product ID],0)),"") -> Morning Cereals | E25: =SUMIFS(tblSalesTransactions[Quantity],tblSalesTransactions[Product ID],A25) -> 505 | F25: =SUMIFS(tblSalesTransactions[Sales Amount],tblSalesTransactions[Product ID],A25) -> 1060500 | G25: =COUNTIFS(tblSalesTransactions[Product ID],A25) -> 5 | H25: =IFERROR(F25/E25,0) -> 2100 | I25: =SUMIFS(tblInventory[Closing Stock Qty],tblInventory[Product ID],A25,tblInventory[Snapshot Date],DATE(2026,12,31)) -> 30 | J25: =SUMIFS(tblInventory[Stock Value],tblInventory[Product ID],A25,tblInventory[Snapshot Date],DATE(2026,12,31)) -> 63000 | K25: =IFERROR(F25/SUM(tblProductAnalysis[Total Sales]),0) -> 0.01759998 | L25: =IFERROR(I25/(E25/12),0) -> 0.71287129 | M25: =RANK(F25,$F$4:$F$59,0)+COUNTIF($F$4:F25,F25)-1 -> 22
A26: P023 | B26: =IFERROR(INDEX(tblProducts[Product Name],MATCH(A26,tblProducts[Product ID],0)),"") -> Granola Chocolate | C26: =IFERROR(INDEX(tblProducts[Brand],MATCH(A26,tblProducts[Product ID],0)),"") -> Morning Harvest | D26: =IFERROR(INDEX(tblProducts[Category],MATCH(A26,tblProducts[Product ID],0)),"") -> Morning Cereals | E26: =SUMIFS(tblSalesTransactions[Quantity],tblSalesTransactions[Product ID],A26) -> 0 | F26: =SUMIFS(tblSalesTransactions[Sales Amount],tblSalesTransactions[Product ID],A26) -> 0 | G26: =COUNTIFS(tblSalesTransactions[Product ID],A26) -> 0 | H26: =IFERROR(F26/E26,0) -> 0 | I26: =SUMIFS(tblInventory[Closing Stock Qty],tblInventory[Product ID],A26,tblInventory[Snapshot Date],DATE(2026,12,31)) -> 30 | J26: =SUMIFS(tblInventory[Stock Value],tblInventory[Product ID],A26,tblInventory[Snapshot Date],DATE(2026,12,31)) -> 63000 | K26: =IFERROR(F26/SUM(tblProductAnalysis[Total Sales]),0) -> 0 | L26: =IFERROR(I26/(E26/12),0) -> 0 | M26: =RANK(F26,$F$4:$F$59,0)+COUNTIF($F$4:F26,F26)-1 -> 42
... A59: P056 | B59: =IFERROR(INDEX(tblProducts[Product Name],MATCH(A59,tblProducts[Product ID],0)),"") -> Filled Croissant Vanilla | C59: =IFERROR(INDEX(tblProducts[Brand],MATCH(A59,tblProducts[Product ID],0)),"") -> Melegatti | D59: =IFERROR(INDEX(tblProducts[Category],MATCH(A59,tblProducts[Product ID],0)),"") -> Cakes & Croissants | E59: =SUMIFS(tblSalesTransactions[Quantity],tblSalesTransactions[Product ID],A59) -> 1445 | F59: =SUMIFS(tblSalesTransactions[Sales Amount],tblSalesTransactions[Product ID],A59) -> 1950750 | G59: =COUNTIFS(tblSalesTransactions[Product ID],A59) -> 12 | H59: =IFERROR(F59/E59,0) -> 1350 | I59: =SUMIFS(tblInventory[Closing Stock Qty],tblInventory[Product ID],A59,tblInventory[Snapshot Date],DATE(2026,12,31)) -> 37 | J59: =SUMIFS(tblInventory[Stock Value],tblInventory[Product ID],A59,tblInventory[Snapshot Date],DATE(2026,12,31)) -> 49950 | K59: =IFERROR(F59/SUM(tblProductAnalysis[Total Sales]),0) -> 0.032374504 | L59: =IFERROR(I59/(E59/12),0) -> 0.30726644 | M59: =RANK(F59,$F$4:$F$59,0)+COUNTIF($F$4:F59,F59)-1 -> 14
E60: =SUBTOTAL(109,tblProductAnalysis[Total Quantity Sold]) -> 38025 | F60: =SUBTOTAL(109,tblProductAnalysis[Total Sales]) -> 60255750 | J60: =SUBTOTAL(109,tblProductAnalysis[Distributor Stock Value]) -> 3553500

Sheet 16_Sales_Forecast
A1: Sales Forecast - Monthly Historical Sales
A3: Month | B3: Month No | C3: Actual Sales | D3: Previous Month Sales | E3: MoM Growth % | F3: 3-Month Moving Average | I3: Month | J3: Actual Sales | K3: Forecast Sales
A4: 46023 | B4: =MONTH(A4) -> 1 | C4: =SUMIFS(tblSalesTransactions[Sales Amount],tblSalesTransactions[Date],">="&A4,tblSalesTransactions[Date],"<"&EDATE(A4,1)) -> 5691250 | I4: =A4 -> 46023 | J4: =C4 -> 5691250
A5: 46054 | B5: =MONTH(A5) -> 2 | C5: =SUMIFS(tblSalesTransactions[Sales Amount],tblSalesTransactions[Date],">="&A5,tblSalesTransactions[Date],"<"&EDATE(A5,1)) -> 4273750 | D5: =C4 -> 5691250 | E5: =IFERROR((C6-D6)/D6,0) -> 0.054752852 | I5: =A5 -> 46054 | J5: =C5 -> 4273750
A6: 46082 | B6: =MONTH(A6) -> 3 | C6: =SUMIFS(tblSalesTransactions[Sales Amount],tblSalesTransactions[Date],">="&A6,tblSalesTransactions[Date],"<"&EDATE(A6,1)) -> 4507750 | D6: =C5 -> 4273750 | E6: =IFERROR((C7-D7)/D7,0) -> -0.13482336 | F6: =AVERAGE(C4:C6) -> 4824250 | I6: =A6 -> 46082 | J6: =C6 -> 4507750
A7: 46113 | B7: =MONTH(A7) -> 4 | C7: =SUMIFS(tblSalesTransactions[Sales Amount],tblSalesTransactions[Date],">="&A7,tblSalesTransactions[Date],"<"&EDATE(A7,1)) -> 3900000 | D7: =C6 -> 4507750 | E7: =IFERROR((C8-D8)/D8,0) -> 0.1800641 | F7: =AVERAGE(C5:C7) -> 4227166.7 | I7: =A7 -> 46113 | J7: =C7 -> 3900000
A8: 46143 | B8: =MONTH(A8) -> 5 | C8: =SUMIFS(tblSalesTransactions[Sales Amount],tblSalesTransactions[Date],">="&A8,tblSalesTransactions[Date],"<"&EDATE(A8,1)) -> 4602250 | D8: =C7 -> 3900000 | E8: =IFERROR((C9-D9)/D9,0) -> 0.027540877 | F8: =AVERAGE(C6:C8) -> 4336666.7 | I8: =A8 -> 46143 | J8: =C8 -> 4602250
A9: 46174 | B9: =MONTH(A9) -> 6 | C9: =SUMIFS(tblSalesTransactions[Sales Amount],tblSalesTransactions[Date],">="&A9,tblSalesTransactions[Date],"<"&EDATE(A9,1)) -> 4729000 | D9: =C8 -> 4602250 | E9: =IFERROR((C10-D10)/D10,0) -> -0.06264538 | F9: =AVERAGE(C7:C9) -> 4410416.7 | I9: =A9 -> 46174 | J9: =C9 -> 4729000
A10: 46204 | B10: =MONTH(A10) -> 7 | C10: =SUMIFS(tblSalesTransactions[Sales Amount],tblSalesTransactions[Date],">="&A10,tblSalesTransactions[Date],"<"&EDATE(A10,1)) -> 4432750 | D10: =C9 -> 4729000 | E10: =IFERROR((C11-D11)/D11,0) -> 0.1125148 | F10: =AVERAGE(C8:C10) -> 4588000 | I10: =A10 -> 46204 | J10: =C10 -> 4432750
A11: 46235 | B11: =MONTH(A11) -> 8 | C11: =SUMIFS(tblSalesTransactions[Sales Amount],tblSalesTransactions[Date],">="&A11,tblSalesTransactions[Date],"<"&EDATE(A11,1)) -> 4931500 | D11: =C10 -> 4432750 | E11: =IFERROR((C12-D12)/D12,0) -> 0.052570212 | F11: =AVERAGE(C9:C11) -> 4697750 | I11: =A11 -> 46235 | J11: =C11 -> 4931500
A12: 46266 | B12: =MONTH(A12) -> 9 | C12: =SUMIFS(tblSalesTransactions[Sales Amount],tblSalesTransactions[Date],">="&A12,tblSalesTransactions[Date],"<"&EDATE(A12,1)) -> 5190750 | D12: =C11 -> 4931500 | E12: =IFERROR((C13-D13)/D13,0) -> 0.051533979 | F12: =AVERAGE(C10:C12) -> 4851666.7 | I12: =A12 -> 46266 | J12: =C12 -> 5190750
A13: 46296 | B13: =MONTH(A13) -> 10 | C13: =SUMIFS(tblSalesTransactions[Sales Amount],tblSalesTransactions[Date],">="&A13,tblSalesTransactions[Date],"<"&EDATE(A13,1)) -> 5458250 | D13: =C12 -> 5190750 | E13: =IFERROR((C14-D14)/D14,0) -> 0.086612009 | F13: =AVERAGE(C11:C13) -> 5193500 | I13: =A13 -> 46296 | J13: =C13 -> 5458250
A14: 46327 | B14: =MONTH(A14) -> 11 | C14: =SUMIFS(tblSalesTransactions[Sales Amount],tblSalesTransactions[Date],">="&A14,tblSalesTransactions[Date],"<"&EDATE(A14,1)) -> 5931000 | D14: =C13 -> 5458250 | E14: =IFERROR((C15-D15)/D15,0) -> 0.11406171 | F14: =AVERAGE(C12:C14) -> 5526666.7 | I14: =A14 -> 46327 | J14: =C14 -> 5931000
A15: 46357 | B15: =MONTH(A15) -> 12 | C15: =SUMIFS(tblSalesTransactions[Sales Amount],tblSalesTransactions[Date],">="&A15,tblSalesTransactions[Date],"<"&EDATE(A15,1)) -> 6607500 | D15: =C14 -> 5931000 | E15: =IFERROR((C16-D16)/D16,0) -> 0 | F15: =AVERAGE(C13:C15) -> 5998916.7 | I15: =A15 -> 46357 | J15: =C15 -> 6607500
I16: =A20 -> 46388 | K16: =B20 -> 5998916.7
I17: =A21 -> 46419 | K17: =B21 -> 6179138.9
I18: =A22 -> 46447 | K18: =B22 -> 6261851.9
A19: Forecast Month | B19: Forecast Sales | C19: Forecast Method | D19: Forecast Basis | F19: Forecast Summary
A20: 46388 | B20: =AVERAGE(C13:C15) -> 5998916.7 | C20: 3-Month Rolling Average — Recursive Forecast | D20: Oct-Dec 2026 actual sales | F20: KPI | G20: Value
A21: 46419 | B21: =AVERAGE(C14:C15,B20) -> 6179138.9 | C21: 3-Month Rolling Average — Recursive Forecast | D21: Nov-Dec 2026 actual + Jan-27 forecast | F21: Last Actual Month | G21: =MAX(tblSalesTransactions[Date]) -> 46384
A22: 46447 | B22: =AVERAGE(C15,B20:B21) -> 6261851.9 | C22: 3-Month Rolling Average — Recursive Forecast | D22: Dec-26 actual + Jan-Feb 2027 forecast | F22: Last 3-Month Avg Sales | G22: =AVERAGE(C13:C15) -> 5998916.7
F23: Jan-27 Forecast | G23: =B20 -> 5998916.7
F24: Feb-27 Forecast | G24: =B21 -> 6179138.9
A25: Note | B25: Explanation | F25: Mar-27 Forecast | G25: =B22 -> 6261851.9
A26: Forecast Type | B26: Short-term sales forecast based on the 3-month moving average method. | F26: Forecast Method | G26: 3-Month Rolling Average
A27: Historical Period | B27: Actual company-to-distributor sales from Jan-2026 to Dec-2026.
A28: Forecast Period | B28: Jan-2027 onward.
A29: Forecast Basis | B29: Forecast values use the average sales of the most recent three months available.
A30: Sales Definition | B30: Sales represent company-to-distributor primary sales; distributor sell-out is not included.
A31: Data Nature | B31: All data in this portfolio workbook is synthetic/illustrative and does not represent actual company results.
A32: Forecast Notes | B32: Forecast values are indicative planning estimates based on a 3-month rolling average. February and March forecasts use recursive forecasting because actual 2027 sales are not available.
B33: Sales represent synthetic company-to-distributor primary sales data for portfolio analysis. Forecasts should not be interpreted as guaranteed future sales.

Sheet 17_Management_Dashboard
A1: 2026 Management View - Synthetic Data - Based on Real-World FMCG Reporting Experience
A2: 2026 Management View - Synthetic Portfolio Data | P2: City ID | Q2: City | R2: Total Sales
P3: C001 | Q3: =IFERROR(INDEX(tblCities[City],MATCH(P3,tblCities[City ID],0)),"") -> Karachi | R3: =SUMIFS(tblSalesTransactions[Sales Amount],tblSalesTransactions[City ID],P3) -> 11422000
A4: TOTAL SALES | D4: TOTAL TARGET | G4: ACHIEVEMENT % | J4: SALES VARIANCE | P4: C002 | Q4: =IFERROR(INDEX(tblCities[City],MATCH(P4,tblCities[City ID],0)),"") -> Lahore | R4: =SUMIFS(tblSalesTransactions[Sales Amount],tblSalesTransactions[City ID],P4) -> 17938000
P5: C003 | Q5: =IFERROR(INDEX(tblCities[City],MATCH(P5,tblCities[City ID],0)),"") -> Islamabad | R5: =SUMIFS(tblSalesTransactions[Sales Amount],tblSalesTransactions[City ID],P5) -> 18894750
P6: C004 | Q6: =IFERROR(INDEX(tblCities[City],MATCH(P6,tblCities[City ID],0)),"") -> Rawalpindi | R6: =SUMIFS(tblSalesTransactions[Sales Amount],tblSalesTransactions[City ID],P6) -> 12001000
A7: =SUM(tblSalesTransactions[Sales Amount]) -> 60255750 | D7: =SUM(tblSalesTargets[Target Amount]) -> 348075000 | G7: =IFERROR(SUM(tblSalesTransactions[Sales Amount])/SUM(tblSalesTargets[Target Amount]),0) -> 0.1731114 | J7: =SUM(tblSalesTransactions[Sales Amount])-SUM(tblSalesTargets[Target Amount]) -> -287819250
A8: Monthly Sales Trend | H8: Target vs Actual Performance
A17: Sales by City | H17: Top Products by Sales
A27: Management Insights
A28: • Overall: 2026 company sales totaled 60.3M against a target of 348.1M, resulting in 17.3% achievement and a negative sales variance of 287.8M.
A29: • Monthly: sales show variation across 2026, indicating uneven sales performance throughout the year.
A30: • City: Islamabad generated the highest company-to-distributor sales among the four cities, making it the largest city-level contributor to 2026 primary sales.
A31: • Product: Pandoro Classico was the highest-selling product in 2026 based on company-to-distributor sales.

Sheet 18_Model_Documentation
A1: Sheet | B1: Purpose | C1: Main Inputs | D1: Main Formulas / Techniques | E1: Automation / Notes
A2: 01_README | B2: Project overview and usage documentation | C2: Workbook scope | D2: Documentation | E2: Explains synthetic-data and business-scope assumptions
A3: 02_Control_Panel | B3: Model controls, statistics and scope | C3: Model parameters and Excel Tables | D3: COUNTA, SUMPRODUCT, linked controls | E3: Selected controls influence downstream calculations
A4: 03_Cities | B4: City master data | C4: City records | D4: Excel Table | E4: Master data
A5: 04_Sales_Team | B5: RSM and salesperson master | C5: Sales team records | D5: Excel Table | E5: Master data
A6: 05_Distributors | B6: Distributor master | C6: Distributor records | D6: Excel Table | E6: Master data
A7: 06_Products | B7: Product/SKU master | C7: Product records | D7: Excel Table | E7: Master data
A8: 07_Calendar | B8: Date dimension | C8: 2026 dates | D8: YEAR, MONTH, TEXT, ROUNDUP, WEEKNUM, WEEKDAY | E8: Supports time-based analysis
A9: 08_Sales_Targets | B9: Monthly salesperson targets | C9: Target records | D9: Excel Table, SUMIFS downstream | E9: Synthetic target-planning dataset
A10: 09_Sales_Transactions | B10: Company-to-distributor sales | C10: Sales transactions | D10: Quantity × Unit Price | E10: Primary sales / sell-in
A11: 10_Inventory | B11: Distributor stock snapshots | C11: Quarterly inventory records | D11: SUMIFS downstream | E11: Selected SKU monitoring sample
A12: 11_Collections | B12: Distributor collections | C12: Invoice/payment records | D12: IF, arithmetic calculations | E12: Tracks collected and outstanding amounts
... A19: 18_Model_Documentation | B19: Technical model documentation | C19: Workbook structure | D19: Documentation | E19: Formula library and methodology reference
A21: Target Planning Methodology
A22: Company Target → City Allocation → Salesperson Allocation → Monthly Seasonality The synthetic 2026 target framework uses a top-down planning concept. The annual company target is allocated across cities using illustrative planning percentages: Karachi 35%, Lahore 30%, Islamabad 20%, and Rawalpindi 15%. Within each city, salesperson targets are conceptually allocated according to assumed territory/distributor potential using a 40% / 35% / 25% allocation. Monthly targets incorporate illustrative seasonality multipliers. These assumptions are synthetic and are not derived from confidential historical company data.
A24: Formula / Technique | B24: Purpose
A25: Quantity × Unit Price | B25: Sales Amount
A26: Invoice Amount - Collected Amount | B26: Outstanding Amount
A27: SUMIFS | B27: Monthly, city, distributor and product aggregation
A28: COUNTIFS | B28: Transaction and condition counts
A29: INDEX + MATCH | B29: Master-data lookups
A30: IFERROR | B30: Error-safe ratios and lookups
A31: IF / AND | B31: Status and indicator classification
A32: RANK | B32: Product sales ranking
A33: AVERAGE | B33: Moving-average and forecast calculations
A34: EDATE / MONTH | B34: Monthly date handling
